{
  "titulo_principal": "PERFIL DE PERSONAGEM - CAPÍTULO 43",
  "conteudo_completo": "═══════════════════════════════════════════════════════════════════════════════\n                            PERFIL DE PERSONAGEM - CAPÍTULO 43\n═══════════════════════════════════════════════════════════════════════════════\n\nGOPĀ\n\nINFORMAÇÕES BÁSICAS\n\nNome e Tradução: Gopā\n                  \"aquela que cuida\"\nTipo: Princesa Śākya / Bodhisattva\nLocalização: Cidade de Kapilavastu, no Salão da Assembleia dos Bodhisattvas chamado \"Luz Iluminadora do Reino do Dharma\"\nStatus: Professora espiritual / Kalyāṇamitra com domínio nos caminhos do samādhi\n\nDESCRIÇÃO FÍSICA\nAparência Visual\n\nCor do Corpo: Não especificada diretamente, mas com uma presença que irradia luz de sabedoria\nCabelo: Não descrito especificamente\nOlhos: Olhos de sabedoria que veem e compreendem os oceanos de reinos búdicos\nBeleza Geral: Aparência de nobreza real, sentada em um trono precioso que ilumina todas as moradas de bodhisattva\nAdornos: Cercada por oitenta e quatro mil mulheres de linhagens reais dedicadas\nVestimentas: Vestimentas reais e apropriadas para sua condição como uma princesa Śākya\n\nCARACTERÍSTICAS ESPIRITUAIS DISTINTIVAS\n\n• Mestra da liberação bodhisattva \"o alcance da visão de todas as maneiras do oceano de samādhis dos bodhisattvas\"\n• Capacidade de ver e compreender kalpas em reinos búdicos tão numerosos quanto os átomos\n• Percepção dos caminhos e práticas dos bodhisattvas através dos tempos\n• Compreensão das manifestações milagrosas e aspectos de iluminação de buddhas\n• Capacidade de guiar de forma eficaz os bodhisattvas no caminho do samādhi\n\nEXPERIÊNCIA MÍSTICA CENTRAL\n\nGopā atinge a liberação bodhisattva chamada \"o alcance da visão de todas as maneiras do oceano de samādhis dos bodhisattvas\". Esta liberação permite:\n\n- Conhecer e compreender todas as existências de seres em kalpas incontáveis\n- Saber todas as portas de entrada na morte e renascimento\n- Compreender os destinos kármicos e realizações espirituais dos seres\n- Conhecer o caminho e práticas dos bodhisattvas dentro do oceano de reinos\n- Ensinar a prática bodhisattva como uma ilusão mágica que conduz à iluminação\n\nLOCALIZAÇÃO E CONTEXTO\n\nSente-se no centro do Salão da Assembleia dos Bodhisattvas em Kapilavastu, um lugar de intensa atividade espiritual e iluminação. É cercada por mulheres de linhagens reais que compartilham uma jornada espiritual em direção à iluminação completa.\n\nCONEXÃO MÍSTICA COM O PASSADO\n\nGopā compartilha entendimento espiritual profundo derivado de seu caminho como bodhisattva e sua reencarnação em diferentes eras para guiar outros no caminho da iluminação. Ela representa a interação cuidadosa e manifestação de práticas espirituais para o benefício de todos os seres.\n\nDESCRIÇÃO GENERATIVA:\n\n\"Crie uma princesa Śākya sentada em um trono precioso que ilumina todos os reinos de bodhisattva dentro de um grandioso salão de assembleia. A personagem deve emanar uma sabedoria e luz serena, cercada por um séquito de mulheres reais, refletindo sua presença espiritual nobre. Ela deve ter uma aparência de nobreza e dignidade, representando sua função de professora e cuidadora espiritual. O ambiente deve ser de um salão iluminado com ornamentos que representam o alcance do Dharma. Fundo branco limpo (blank background).\"\n",
  "dados_estruturados": {
    "informacoes_basicas": {
      "nome_e_traducao": "Gopā",
      "tipo": "Princesa Śākya / Bodhisattva",
      "localizacao": "Cidade de Kapilavastu, no Salão da Assembleia dos Bodhisattvas chamado \"Luz Iluminadora do Reino do Dharma\"",
      "status": "Professora espiritual / Kalyāṇamitra com domínio nos caminhos do samādhi"
    },
    "descricao_fisica": {
      "cor_do_corpo": "Não especificada diretamente, mas com uma presença que irradia luz de sabedoria",
      "cabelo": "Não descrito especificamente",
      "olhos": "Olhos de sabedoria que veem e compreendem os oceanos de reinos búdicos",
      "beleza_geral": "Aparência de nobreza real, sentada em um trono precioso que ilumina todas as moradas de bodhisattva",
      "adornos": "Cercada por oitenta e quatro mil mulheres de linhagens reais dedicadas",
      "vestimentas": "Vestimentas reais e apropriadas para sua condição como uma princesa Śākya"
    },
    "caracteristicas_espirituais": [
      "• Mestra da liberação bodhisattva \"o alcance da visão de todas as maneiras do oceano de samādhis dos bodhisattvas\"",
      "• Capacidade de ver e compreender kalpas em reinos búdicos tão numerosos quanto os átomos",
      "• Percepção dos caminhos e práticas dos bodhisattvas através dos tempos",
      "• Compreensão das manifestações milagrosas e aspectos de iluminação de buddhas",
      "• Capacidade de guiar de forma eficaz os bodhisattvas no caminho do samādhi"
    ],
    "experiencia_mistica": "Gopā atinge a liberação bodhisattva chamada \"o alcance da visão de todas as maneiras do oceano de samādhis dos bodhisattvas\". Esta liberação permite:\n\n- Conhecer e compreender todas as existências de seres em kalpas incontáveis\n- Saber todas as portas de entrada na morte e renascimento\n- Compreender os destinos kármicos e realizações espirituais dos seres\n- Conhecer o caminho e práticas dos bodhisattvas dentro do oceano de reinos\n- Ensinar a prática bodhisattva como uma ilusão mágica que conduz à iluminação",
    "localizacao_contexto": "Sente-se no centro do Salão da Assembleia dos Bodhisattvas em Kapilavastu, um lugar de intensa atividade espiritual e iluminação. É cercada por mulheres de linhagens reais que compartilham uma jornada espiritual em direção à iluminação completa.\n\nCONEXÃO MÍSTICA COM O PASSADO\n\nGopā compartilha entendimento espiritual profundo derivado de seu caminho como bodhisattva e sua reencarnação em diferentes eras para guiar outros no caminho da iluminação. Ela representa a interação cuidadosa e manifestação de práticas espirituais para o benefício de todos os seres.",
    "prompt_ia": "\"Crie uma princesa Śākya sentada em um trono precioso que ilumina todos os reinos de bodhisattva dentro de um grandioso salão de assembleia. A personagem deve emanar uma sabedoria e luz serena, cercada por um séquito de mulheres reais, refletindo sua presença espiritual nobre. Ela deve ter uma aparência de nobreza e dignidade, representando sua função de professora e cuidadora espiritual. O ambiente deve ser de um salão iluminado com ornamentos que representam o alcance do Dharma. Fundo branco limpo (blank background).\""
  },
  "secoes_organizadas": [
    {
      "titulo": "INFORMAÇÕES BÁSICAS",
      "linhas": [
        "Nome e Tradução: Gopā",
        "                  \"aquela que cuida\"",
        "Tipo: Princesa Śākya / Bodhisattva",
        "Localização: Cidade de Kapilavastu, no Salão da Assembleia dos Bodhisattvas chamado \"Luz Iluminadora do Reino do Dharma\"",
        "Status: Professora espiritual / Kalyāṇamitra com domínio nos caminhos do samādhi"
      ],
      "conteudo": "Nome e Tradução: Gopā\n                  \"aquela que cuida\"\nTipo: Princesa Śākya / Bodhisattva\nLocalização: Cidade de Kapilavastu, no Salão da Assembleia dos Bodhisattvas chamado \"Luz Iluminadora do Reino do Dharma\"\nStatus: Professora espiritual / Kalyāṇamitra com domínio nos caminhos do samādhi"
    },
    {
      "titulo": "DESCRIÇÃO FÍSICA",
      "linhas": [
        "Aparência Visual",
        "",
        "Cor do Corpo: Não especificada diretamente, mas com uma presença que irradia luz de sabedoria",
        "Cabelo: Não descrito especificamente",
        "Olhos: Olhos de sabedoria que veem e compreendem os oceanos de reinos búdicos",
        "Beleza Geral: Aparência de nobreza real, sentada em um trono precioso que ilumina todas as moradas de bodhisattva",
        "Adornos: Cercada por oitenta e quatro mil mulheres de linhagens reais dedicadas",
        "Vestimentas: Vestimentas reais e apropriadas para sua condição como uma princesa Śākya"
      ],
      "conteudo": "Aparência Visual\n\nCor do Corpo: Não especificada diretamente, mas com uma presença que irradia luz de sabedoria\nCabelo: Não descrito especificamente\nOlhos: Olhos de sabedoria que veem e compreendem os oceanos de reinos búdicos\nBeleza Geral: Aparência de nobreza real, sentada em um trono precioso que ilumina todas as moradas de bodhisattva\nAdornos: Cercada por oitenta e quatro mil mulheres de linhagens reais dedicadas\nVestimentas: Vestimentas reais e apropriadas para sua condição como uma princesa Śākya"
    },
    {
      "titulo": "CARACTERÍSTICAS ESPIRITUAIS DISTINTIVAS",
      "linhas": [
        "• Mestra da liberação bodhisattva \"o alcance da visão de todas as maneiras do oceano de samādhis dos bodhisattvas\"",
        "• Capacidade de ver e compreender kalpas em reinos búdicos tão numerosos quanto os átomos",
        "• Percepção dos caminhos e práticas dos bodhisattvas através dos tempos",
        "• Compreensão das manifestações milagrosas e aspectos de iluminação de buddhas",
        "• Capacidade de guiar de forma eficaz os bodhisattvas no caminho do samādhi"
      ],
      "conteudo": "• Mestra da liberação bodhisattva \"o alcance da visão de todas as maneiras do oceano de samādhis dos bodhisattvas\"\n• Capacidade de ver e compreender kalpas em reinos búdicos tão numerosos quanto os átomos\n• Percepção dos caminhos e práticas dos bodhisattvas através dos tempos\n• Compreensão das manifestações milagrosas e aspectos de iluminação de buddhas\n• Capacidade de guiar de forma eficaz os bodhisattvas no caminho do samādhi"
    },
    {
      "titulo": "EXPERIÊNCIA MÍSTICA CENTRAL",
      "linhas": [
        "Gopā atinge a liberação bodhisattva chamada \"o alcance da visão de todas as maneiras do oceano de samādhis dos bodhisattvas\". Esta liberação permite:",
        "",
        "- Conhecer e compreender todas as existências de seres em kalpas incontáveis",
        "- Saber todas as portas de entrada na morte e renascimento",
        "- Compreender os destinos kármicos e realizações espirituais dos seres",
        "- Conhecer o caminho e práticas dos bodhisattvas dentro do oceano de reinos",
        "- Ensinar a prática bodhisattva como uma ilusão mágica que conduz à iluminação"
      ],
      "conteudo": "Gopā atinge a liberação bodhisattva chamada \"o alcance da visão de todas as maneiras do oceano de samādhis dos bodhisattvas\". Esta liberação permite:\n\n- Conhecer e compreender todas as existências de seres em kalpas incontáveis\n- Saber todas as portas de entrada na morte e renascimento\n- Compreender os destinos kármicos e realizações espirituais dos seres\n- Conhecer o caminho e práticas dos bodhisattvas dentro do oceano de reinos\n- Ensinar a prática bodhisattva como uma ilusão mágica que conduz à iluminação"
    },
    {
      "titulo": "LOCALIZAÇÃO E CONTEXTO",
      "linhas": [
        "Sente-se no centro do Salão da Assembleia dos Bodhisattvas em Kapilavastu, um lugar de intensa atividade espiritual e iluminação. É cercada por mulheres de linhagens reais que compartilham uma jornada espiritual em direção à iluminação completa.",
        "",
        "CONEXÃO MÍSTICA COM O PASSADO",
        "",
        "Gopā compartilha entendimento espiritual profundo derivado de seu caminho como bodhisattva e sua reencarnação em diferentes eras para guiar outros no caminho da iluminação. Ela representa a interação cuidadosa e manifestação de práticas espirituais para o benefício de todos os seres."
      ],
      "conteudo": "Sente-se no centro do Salão da Assembleia dos Bodhisattvas em Kapilavastu, um lugar de intensa atividade espiritual e iluminação. É cercada por mulheres de linhagens reais que compartilham uma jornada espiritual em direção à iluminação completa.\n\nCONEXÃO MÍSTICA COM O PASSADO\n\nGopā compartilha entendimento espiritual profundo derivado de seu caminho como bodhisattva e sua reencarnação em diferentes eras para guiar outros no caminho da iluminação. Ela representa a interação cuidadosa e manifestação de práticas espirituais para o benefício de todos os seres."
    },
    {
      "titulo": "DESCRIÇÃO GENERATIVA:",
      "linhas": [
        "\"Crie uma princesa Śākya sentada em um trono precioso que ilumina todos os reinos de bodhisattva dentro de um grandioso salão de assembleia. A personagem deve emanar uma sabedoria e luz serena, cercada por um séquito de mulheres reais, refletindo sua presença espiritual nobre. Ela deve ter uma aparência de nobreza e dignidade, representando sua função de professora e cuidadora espiritual. O ambiente deve ser de um salão iluminado com ornamentos que representam o alcance do Dharma. Fundo branco limpo (blank background).\""
      ],
      "conteudo": "\"Crie uma princesa Śākya sentada em um trono precioso que ilumina todos os reinos de bodhisattva dentro de um grandioso salão de assembleia. A personagem deve emanar uma sabedoria e luz serena, cercada por um séquito de mulheres reais, refletindo sua presença espiritual nobre. Ela deve ter uma aparência de nobreza e dignidade, representando sua função de professora e cuidadora espiritual. O ambiente deve ser de um salão iluminado com ornamentos que representam o alcance do Dharma. Fundo branco limpo (blank background).\""
    }
  ]
}