{
  "titulo_principal": "PERFIL DE PERSONAGEM - CAPÍTULO 26",
  "conteudo_completo": "═══════════════════════════════════════════════════════════════════════════════  \n                            PERFIL DE PERSONAGEM - CAPÍTULO 26  \n═══════════════════════════════════════════════════════════════════════════════\n\nNOME DO PERSONAGEM: Jayottama\n\nINFORMAÇÕES BÁSICAS\n\nNome e Tradução: Jayottama (possivelmente \"Vitória Suprema\" ou \"Excelência Superior\")\nTipo: Chefe Mercador (Head Merchant)\nLocalização: Cidade de Nandihāra, na floresta de árvores ashoka chamada Vicitra dhvaja\nStatus: Mestre espiritual que ensina o Dharma para householders e diversos seres\n\nDESCRIÇÃO FÍSICA\nAparência Visual\n\nCor do Corpo: Não especificada\nCabelo: Não especificado\nOlhos: Não especificado\nBeleza Geral: Não especificada fisicamente, mas descrito como tendo presença magnética que atrai milhares de householders\nAdornos: Não especificados\nVestimentas: Não especificadas (presumivelmente vestes de mercador próspero)\n\nCARACTERÍSTICAS ESPIRITUAIS DISTINTIVAS\n\n- Purifica o portal para a conduta bodhisattva onipresente através do poder da realização de milagres não-compostos\n- Reside na \"ausência de existência\" enquanto manifesta atividade em todos os reinos\n- Ensina o Dharma simultaneamente em incontáveis mundos e reinos\n- Especialista em pacificar conflitos, disputas e guerras\n- Mestre em converter seres dos dez não-virtuosos para caminhos virtuosos\n\nEXPERIÊNCIA MÍSTICA CENTRAL\n\nJayottama domina o \"portal para a conduta bodhisattva onipresente pura\" baseado na \"exibição imaculada de milagres não-compostos baseados na ausência de existência\". Ele ensina simultaneamente em bilhões de universos, todos os paraísos, mundos de nāgas, yakṣas, rākṣasas, humanos e todos os seres dos reinos do desejo.\n\nLOCALIZAÇÃO E CONTEXTO\n\nEncontrado na floresta de ashoka chamada Vicitra dhvaja, no lado leste da cidade de Nandihāra, cercado por milhares de householders discutindo deveres cívicos. Ensina o Dharma para eliminar egoísmo, possessividade, apego e despertar a aspiração à iluminação.\n\n{DESCRIÇÃO GENERATIVA: Create a wise, prosperous merchant teacher sitting in a forest of ashoka trees, surrounded by householders in discussion. He should have a dignified, authoritative presence befitting a spiritual master who teaches across multiple realms. Clothing should reflect a successful merchant - fine robes but not overly ornate. Setting: ashoka forest called Vicitra dhvaja near the eastern edge of Nandihāra town. Blank background.}\n",
  "dados_estruturados": {
    "informacoes_basicas": {
      "nome_e_traducao": "Jayottama (possivelmente \"Vitória Suprema\" ou \"Excelência Superior\")",
      "tipo": "Chefe Mercador (Head Merchant)",
      "localizacao": "Cidade de Nandihāra, na floresta de árvores ashoka chamada Vicitra dhvaja",
      "status": "Mestre espiritual que ensina o Dharma para householders e diversos seres"
    },
    "descricao_fisica": {
      "cor_do_corpo": "Não especificada",
      "cabelo": "Não especificado",
      "olhos": "Não especificado",
      "beleza_geral": "Não especificada fisicamente, mas descrito como tendo presença magnética que atrai milhares de householders",
      "adornos": "Não especificados",
      "vestimentas": "Não especificadas (presumivelmente vestes de mercador próspero)"
    },
    "caracteristicas_espirituais": [
      "- Purifica o portal para a conduta bodhisattva onipresente através do poder da realização de milagres não-compostos",
      "- Reside na \"ausência de existência\" enquanto manifesta atividade em todos os reinos",
      "- Ensina o Dharma simultaneamente em incontáveis mundos e reinos",
      "- Especialista em pacificar conflitos, disputas e guerras",
      "- Mestre em converter seres dos dez não-virtuosos para caminhos virtuosos"
    ],
    "experiencia_mistica": "Jayottama domina o \"portal para a conduta bodhisattva onipresente pura\" baseado na \"exibição imaculada de milagres não-compostos baseados na ausência de existência\". Ele ensina simultaneamente em bilhões de universos, todos os paraísos, mundos de nāgas, yakṣas, rākṣasas, humanos e todos os seres dos reinos do desejo.",
    "localizacao_contexto": "Encontrado na floresta de ashoka chamada Vicitra dhvaja, no lado leste da cidade de Nandihāra, cercado por milhares de householders discutindo deveres cívicos. Ensina o Dharma para eliminar egoísmo, possessividade, apego e despertar a aspiração à iluminação."
  },
  "secoes_organizadas": [
    {
      "titulo": "INFORMAÇÕES BÁSICAS",
      "linhas": [
        "Nome e Tradução: Jayottama (possivelmente \"Vitória Suprema\" ou \"Excelência Superior\")",
        "Tipo: Chefe Mercador (Head Merchant)",
        "Localização: Cidade de Nandihāra, na floresta de árvores ashoka chamada Vicitra dhvaja",
        "Status: Mestre espiritual que ensina o Dharma para householders e diversos seres"
      ],
      "conteudo": "Nome e Tradução: Jayottama (possivelmente \"Vitória Suprema\" ou \"Excelência Superior\")\nTipo: Chefe Mercador (Head Merchant)\nLocalização: Cidade de Nandihāra, na floresta de árvores ashoka chamada Vicitra dhvaja\nStatus: Mestre espiritual que ensina o Dharma para householders e diversos seres"
    },
    {
      "titulo": "DESCRIÇÃO FÍSICA",
      "linhas": [
        "Aparência Visual",
        "",
        "Cor do Corpo: Não especificada",
        "Cabelo: Não especificado",
        "Olhos: Não especificado",
        "Beleza Geral: Não especificada fisicamente, mas descrito como tendo presença magnética que atrai milhares de householders",
        "Adornos: Não especificados",
        "Vestimentas: Não especificadas (presumivelmente vestes de mercador próspero)"
      ],
      "conteudo": "Aparência Visual\n\nCor do Corpo: Não especificada\nCabelo: Não especificado\nOlhos: Não especificado\nBeleza Geral: Não especificada fisicamente, mas descrito como tendo presença magnética que atrai milhares de householders\nAdornos: Não especificados\nVestimentas: Não especificadas (presumivelmente vestes de mercador próspero)"
    },
    {
      "titulo": "CARACTERÍSTICAS ESPIRITUAIS DISTINTIVAS",
      "linhas": [
        "- Purifica o portal para a conduta bodhisattva onipresente através do poder da realização de milagres não-compostos",
        "- Reside na \"ausência de existência\" enquanto manifesta atividade em todos os reinos",
        "- Ensina o Dharma simultaneamente em incontáveis mundos e reinos",
        "- Especialista em pacificar conflitos, disputas e guerras",
        "- Mestre em converter seres dos dez não-virtuosos para caminhos virtuosos"
      ],
      "conteudo": "- Purifica o portal para a conduta bodhisattva onipresente através do poder da realização de milagres não-compostos\n- Reside na \"ausência de existência\" enquanto manifesta atividade em todos os reinos\n- Ensina o Dharma simultaneamente em incontáveis mundos e reinos\n- Especialista em pacificar conflitos, disputas e guerras\n- Mestre em converter seres dos dez não-virtuosos para caminhos virtuosos"
    },
    {
      "titulo": "EXPERIÊNCIA MÍSTICA CENTRAL",
      "linhas": [
        "Jayottama domina o \"portal para a conduta bodhisattva onipresente pura\" baseado na \"exibição imaculada de milagres não-compostos baseados na ausência de existência\". Ele ensina simultaneamente em bilhões de universos, todos os paraísos, mundos de nāgas, yakṣas, rākṣasas, humanos e todos os seres dos reinos do desejo."
      ],
      "conteudo": "Jayottama domina o \"portal para a conduta bodhisattva onipresente pura\" baseado na \"exibição imaculada de milagres não-compostos baseados na ausência de existência\". Ele ensina simultaneamente em bilhões de universos, todos os paraísos, mundos de nāgas, yakṣas, rākṣasas, humanos e todos os seres dos reinos do desejo."
    },
    {
      "titulo": "LOCALIZAÇÃO E CONTEXTO",
      "linhas": [
        "Encontrado na floresta de ashoka chamada Vicitra dhvaja, no lado leste da cidade de Nandihāra, cercado por milhares de householders discutindo deveres cívicos. Ensina o Dharma para eliminar egoísmo, possessividade, apego e despertar a aspiração à iluminação."
      ],
      "conteudo": "Encontrado na floresta de ashoka chamada Vicitra dhvaja, no lado leste da cidade de Nandihāra, cercado por milhares de householders discutindo deveres cívicos. Ensina o Dharma para eliminar egoísmo, possessividade, apego e despertar a aspiração à iluminação."
    }
  ]
}