{
  "titulo_principal": "Título não identificado",
  "conteudo_completo": "NOME DO PERSONAGEM\n\nJayoṣmāyatana\n\nINFORMAÇÕES BÁSICAS\n\nNome e Tradução: Jayoṣmāyatana (Morada da Vitória/Triunfo)\nTipo: Brâmane asceta\nLocalização: Terra de Īṣāṇa\nStatus: Mestre da liberação bodhisattva \"domínio incessante\", praticante de ascetismo extremo\n\nDESCRIÇÃO FÍSICA\nAparência Visual\n\nCor do Corpo: Não especificado diretamente\nCabelo: Não especificado\nOlhos: Possui poder de abalar picos do Meru apenas com o olhar\nBeleza Geral: Aparência de asceta praticando austeridades extremas\nAdornos: Não especificado\nVestimentas: Vestimentas de asceta (não detalhadas)\n\nPRÁTICA ASCÉTICA EXTREMA\n\nConfiguração da prática dos \"cinco calores\":\n- Fogos do tamanho de montanhas acesos nos quatro lados\n- Precipício de grande montanha acima\n- Caminho de navalhas levando ao topo\n- Grande massa de fogo onde seres devem pular\n\nCARACTERÍSTICAS ESPIRITUAIS DISTINTIVAS\n\n- Mestre da liberação bodhisattva \"domínio incessante\"\n- Praticante da base para realizar onisciência\n- Praticante de ascetismo extremo (cinco calores)\n- Poder de transformar seres apenas através de sua disciplina feroz\n- Capacidade de abalar montanhas Meru com o olhar\n- Luz dos fogos alcança até o inferno Avīci\n\nPODER TRANSFORMATIVO DA PRÁTICA\n\nEfeitos em seres celestiais durante a prática dos cinco calores:\n\n**Brahmās Poderosos:**\n- Cessaram prazer em seus estados\n- Perderam gosto por dhyāna\n- Abandonaram visões errôneas\n- Desenvolveram grande amor e compaixão\n- Obtiveram aspiração inabalável à iluminação\n\n**Māras:**\n- Radiância ofuscou suas residências e posses\n- Cessaram prazer em suas moradas\n- Mentes foram curadas\n- Desenvolveram aspiração à iluminação\n- Tornaram-se irreversíveis no caminho\n\n**Reis Devas Vaśavartin:**\n- Cessaram deleite em residências\n- Ganharam controle sobre próprias mentes\n- Obtiveram poder sobre kleśas\n- Adquiriram poder de renascer onde desejam\n- Ganharam poder sobre estados meditativos\n\n**Reis Devas Sunirmita:**\n- Luz purificou e iluminou palácios aéreos\n- Cessaram deleite em apsarases\n- Perderam prazer no bem-aventurança do desejo\n- Mentes purificadas e iluminadas\n- Obtiveram conhecimento das dez forças\n\n**Reis Devas Saṃtuṣita:**\n- Cessaram deleite em residências\n- Não mais dependentes de objetos sensoriais\n- Mentes ganharam contentamento\n- Criaram raízes de mérito\n- Desenvolveram aspiração à iluminação\n\n**Reis Devas Suyāma:**\n- Cessaram deleite em canções divinas\n- Afastaram-se de todos os prazeres dos desejos\n- Atingiram todo o Buddhadharma\n\n**Śakras (Senhores dos Devas):**\n- Cessaram deleite em palácios e parques\n- Abandonaram música divina e canções\n- Renunciaram a todos os prazeres dos desejos\n- Desenvolveram aspiração à iluminação suprema\n\n**Nāgas (Airāvata, Nanda, Upananda):**\n- Luz eliminou chuvas de areia e medo dos garuḍas\n- Pacificou raiva e refrescou corpos\n- Repudiaram caminhos malignos dos nāgas\n- Confessaram transgressões\n- Estabelecidos na onisciência\n\n**Senhores Yakṣa:**\n- Desenvolveram mente amorosa em relação aos humanos\n- Yakṣas, rākṣasas e kumbhāṇḍas cessaram violência\n- Corpos e mentes tornaram-se bem-aventurados\n- Multidão de seres desenvolveu aspiração à iluminação\n\n**Senhores Gandharva:**\n- Luz iluminou suas moradas\n- Experienciaram bem-aventurança inconcebível\n- Progrediram irreversivelmente à iluminação\n\n**Senhores Asura:**\n- Mundo asura tremeu com oceanos e montanhas\n- Arrogância e orgulho foram dominados\n- Abandonaram toda decepção\n- Estabelecidos na natureza verdadeira dos fenômenos\n\n**Senhores Garuḍa:**\n- Manifestaram-se como jovens brâmanes belos\n- Ficaram assustados e consternados\n- Praticaram grande amor e compaixão\n- Aplicaram-se a salvar seres no pântano do desejo\n\n**Senhores Kinnara:**\n- Sons de \"Buda\", \"Dharma\", \"Saṅgha\" emergiram de suas árvores\n- Instrumentos musicais ressoaram nomes de Tathāgatas\n- Escutaram sobre atividades bodhisattva em mundos infinitos\n- Experimentaram bem-aventurança através dos sons sagrados\n\n**Devas do Reino do Desejo:**\n- Luz alcançou até inferno Avīci\n- Extinguiu sofrimentos de seres nos infernos\n- Renunciaram ao deleite nos desejos\n- Oraram pela iluminação de seres ilimitados\n\nTESTE DE FÉ E CONFIANÇA\n\nDesafio inicial:\n- Ordena Sudhana a subir montanha por caminho de navalhas\n- Instrui saltar no fogo\n- Sudhana inicialmente duvida se é māra ou kalyāṇamitra\n- Dez mil seres celestiais testemunham em favor do brâmane\n\nResultado do teste:\n- Sudhana obedece e sobe o caminho de navalhas\n- Pula no fogo e experimenta bem-aventurança\n- Atinge samādhi \"completamente estável\" subindo\n- Atinge samādhi \"percebendo bem-aventurança da paz\" no fogo\n- Descobre que fogo e navalhas são bem-aventurados ao toque\n\nLIBERAÇÃO \"DOMÍNIO INCESSANTE\"\n\nCaracterísticas da liberação:\n- Transforma aparentes obstáculos em bênçãos\n- Converte experiências dolorosas em bem-aventurança\n- Permite prática ascética que beneficia incontáveis seres\n- Demonstra poder da mente sobre percepções físicas\n- Ensina que verdadeiros obstáculos são mentais, não físicos\n\nENSINAMENTO SOBRE OBEDIÊNCIA AO GURU\n\nVerso recitado a Sudhana:\n\"O bodhisattva que segue com sucesso as instruções\nE que tem atenção para não desobedecer as palavras do guru\nRealizará com sucesso todos os objetivos e\nAtingirá com sucesso a sabedoria da budidade, iluminado sob a Árvore Bodhi\"\n\nLOCALIZAÇÃO E CONTEXTO\n\n- Pratica na terra de Īṣāṇa\n- Realiza ascetismo em local com precipícios e fogos montanhosos\n- Centro de transformação para seres de todos os reinos\n- Local de teste definitivo de fé na orientação espiritual\n- Demonstração de que aparências podem enganar no caminho espiritual\n",
  "dados_estruturados": {
    "informacoes_basicas": {
      "nome_e_traducao": "Jayoṣmāyatana (Morada da Vitória/Triunfo)",
      "tipo": "Brâmane asceta",
      "localizacao": "Terra de Īṣāṇa",
      "status": "Mestre da liberação bodhisattva \"domínio incessante\", praticante de ascetismo extremo"
    },
    "descricao_fisica": {
      "cor_do_corpo": "Não especificado diretamente",
      "cabelo": "Não especificado",
      "olhos": "Possui poder de abalar picos do Meru apenas com o olhar",
      "beleza_geral": "Aparência de asceta praticando austeridades extremas",
      "adornos": "Não especificado",
      "vestimentas": "Vestimentas de asceta (não detalhadas)",
      "configuração_da_prática_dos_\"cinco_calores\"": ""
    },
    "caracteristicas_espirituais": [
      "- Mestre da liberação bodhisattva \"domínio incessante\"",
      "- Praticante da base para realizar onisciência",
      "- Praticante de ascetismo extremo (cinco calores)",
      "- Poder de transformar seres apenas através de sua disciplina feroz",
      "- Capacidade de abalar montanhas Meru com o olhar",
      "- Luz dos fogos alcança até o inferno Avīci",
      "",
      "PODER TRANSFORMATIVO DA PRÁTICA",
      "",
      "Efeitos em seres celestiais durante a prática dos cinco calores:",
      "",
      "**Brahmās Poderosos:**",
      "- Cessaram prazer em seus estados",
      "- Perderam gosto por dhyāna",
      "- Abandonaram visões errôneas",
      "- Desenvolveram grande amor e compaixão",
      "- Obtiveram aspiração inabalável à iluminação",
      "",
      "**Māras:**",
      "- Radiância ofuscou suas residências e posses",
      "- Cessaram prazer em suas moradas",
      "- Mentes foram curadas",
      "- Desenvolveram aspiração à iluminação",
      "- Tornaram-se irreversíveis no caminho",
      "",
      "**Reis Devas Vaśavartin:**",
      "- Cessaram deleite em residências",
      "- Ganharam controle sobre próprias mentes",
      "- Obtiveram poder sobre kleśas",
      "- Adquiriram poder de renascer onde desejam",
      "- Ganharam poder sobre estados meditativos",
      "",
      "**Reis Devas Sunirmita:**",
      "- Luz purificou e iluminou palácios aéreos",
      "- Cessaram deleite em apsarases",
      "- Perderam prazer no bem-aventurança do desejo",
      "- Mentes purificadas e iluminadas",
      "- Obtiveram conhecimento das dez forças",
      "",
      "**Reis Devas Saṃtuṣita:**",
      "- Cessaram deleite em residências",
      "- Não mais dependentes de objetos sensoriais",
      "- Mentes ganharam contentamento",
      "- Criaram raízes de mérito",
      "- Desenvolveram aspiração à iluminação",
      "",
      "**Reis Devas Suyāma:**",
      "- Cessaram deleite em canções divinas",
      "- Afastaram-se de todos os prazeres dos desejos",
      "- Atingiram todo o Buddhadharma",
      "",
      "**Śakras (Senhores dos Devas):**",
      "- Cessaram deleite em palácios e parques",
      "- Abandonaram música divina e canções",
      "- Renunciaram a todos os prazeres dos desejos",
      "- Desenvolveram aspiração à iluminação suprema",
      "",
      "**Nāgas (Airāvata, Nanda, Upananda):**",
      "- Luz eliminou chuvas de areia e medo dos garuḍas",
      "- Pacificou raiva e refrescou corpos",
      "- Repudiaram caminhos malignos dos nāgas",
      "- Confessaram transgressões",
      "- Estabelecidos na onisciência",
      "",
      "**Senhores Yakṣa:**",
      "- Desenvolveram mente amorosa em relação aos humanos",
      "- Yakṣas, rākṣasas e kumbhāṇḍas cessaram violência",
      "- Corpos e mentes tornaram-se bem-aventurados",
      "- Multidão de seres desenvolveu aspiração à iluminação",
      "",
      "**Senhores Gandharva:**",
      "- Luz iluminou suas moradas",
      "- Experienciaram bem-aventurança inconcebível",
      "- Progrediram irreversivelmente à iluminação",
      "",
      "**Senhores Asura:**",
      "- Mundo asura tremeu com oceanos e montanhas",
      "- Arrogância e orgulho foram dominados",
      "- Abandonaram toda decepção",
      "- Estabelecidos na natureza verdadeira dos fenômenos",
      "",
      "**Senhores Garuḍa:**",
      "- Manifestaram-se como jovens brâmanes belos",
      "- Ficaram assustados e consternados",
      "- Praticaram grande amor e compaixão",
      "- Aplicaram-se a salvar seres no pântano do desejo",
      "",
      "**Senhores Kinnara:**",
      "- Sons de \"Buda\", \"Dharma\", \"Saṅgha\" emergiram de suas árvores",
      "- Instrumentos musicais ressoaram nomes de Tathāgatas",
      "- Escutaram sobre atividades bodhisattva em mundos infinitos",
      "- Experimentaram bem-aventurança através dos sons sagrados",
      "",
      "**Devas do Reino do Desejo:**",
      "- Luz alcançou até inferno Avīci",
      "- Extinguiu sofrimentos de seres nos infernos",
      "- Renunciaram ao deleite nos desejos",
      "- Oraram pela iluminação de seres ilimitados",
      "",
      "TESTE DE FÉ E CONFIANÇA",
      "",
      "Desafio inicial:",
      "- Ordena Sudhana a subir montanha por caminho de navalhas",
      "- Instrui saltar no fogo",
      "- Sudhana inicialmente duvida se é māra ou kalyāṇamitra",
      "- Dez mil seres celestiais testemunham em favor do brâmane",
      "",
      "Resultado do teste:",
      "- Sudhana obedece e sobe o caminho de navalhas",
      "- Pula no fogo e experimenta bem-aventurança",
      "- Atinge samādhi \"completamente estável\" subindo",
      "- Atinge samādhi \"percebendo bem-aventurança da paz\" no fogo",
      "- Descobre que fogo e navalhas são bem-aventurados ao toque",
      "",
      "LIBERAÇÃO \"DOMÍNIO INCESSANTE\"",
      "",
      "Características da liberação:",
      "- Transforma aparentes obstáculos em bênçãos",
      "- Converte experiências dolorosas em bem-aventurança",
      "- Permite prática ascética que beneficia incontáveis seres",
      "- Demonstra poder da mente sobre percepções físicas",
      "- Ensina que verdadeiros obstáculos são mentais, não físicos",
      "",
      "ENSINAMENTO SOBRE OBEDIÊNCIA AO GURU",
      "",
      "Verso recitado a Sudhana:",
      "\"O bodhisattva que segue com sucesso as instruções",
      "E que tem atenção para não desobedecer as palavras do guru",
      "Realizará com sucesso todos os objetivos e",
      "Atingirá com sucesso a sabedoria da budidade, iluminado sob a Árvore Bodhi\""
    ],
    "localizacao_contexto": "- Pratica na terra de Īṣāṇa\n- Realiza ascetismo em local com precipícios e fogos montanhosos\n- Centro de transformação para seres de todos os reinos\n- Local de teste definitivo de fé na orientação espiritual\n- Demonstração de que aparências podem enganar no caminho espiritual"
  },
  "secoes_organizadas": [
    {
      "titulo": "NOME DO PERSONAGEM",
      "linhas": [
        "Jayoṣmāyatana"
      ],
      "conteudo": "Jayoṣmāyatana"
    },
    {
      "titulo": "INFORMAÇÕES BÁSICAS",
      "linhas": [
        "Nome e Tradução: Jayoṣmāyatana (Morada da Vitória/Triunfo)",
        "Tipo: Brâmane asceta",
        "Localização: Terra de Īṣāṇa",
        "Status: Mestre da liberação bodhisattva \"domínio incessante\", praticante de ascetismo extremo"
      ],
      "conteudo": "Nome e Tradução: Jayoṣmāyatana (Morada da Vitória/Triunfo)\nTipo: Brâmane asceta\nLocalização: Terra de Īṣāṇa\nStatus: Mestre da liberação bodhisattva \"domínio incessante\", praticante de ascetismo extremo"
    },
    {
      "titulo": "DESCRIÇÃO FÍSICA",
      "linhas": [
        "Aparência Visual",
        "",
        "Cor do Corpo: Não especificado diretamente",
        "Cabelo: Não especificado",
        "Olhos: Possui poder de abalar picos do Meru apenas com o olhar",
        "Beleza Geral: Aparência de asceta praticando austeridades extremas",
        "Adornos: Não especificado",
        "Vestimentas: Vestimentas de asceta (não detalhadas)",
        "",
        "PRÁTICA ASCÉTICA EXTREMA",
        "",
        "Configuração da prática dos \"cinco calores\":",
        "- Fogos do tamanho de montanhas acesos nos quatro lados",
        "- Precipício de grande montanha acima",
        "- Caminho de navalhas levando ao topo",
        "- Grande massa de fogo onde seres devem pular"
      ],
      "conteudo": "Aparência Visual\n\nCor do Corpo: Não especificado diretamente\nCabelo: Não especificado\nOlhos: Possui poder de abalar picos do Meru apenas com o olhar\nBeleza Geral: Aparência de asceta praticando austeridades extremas\nAdornos: Não especificado\nVestimentas: Vestimentas de asceta (não detalhadas)\n\nPRÁTICA ASCÉTICA EXTREMA\n\nConfiguração da prática dos \"cinco calores\":\n- Fogos do tamanho de montanhas acesos nos quatro lados\n- Precipício de grande montanha acima\n- Caminho de navalhas levando ao topo\n- Grande massa de fogo onde seres devem pular"
    },
    {
      "titulo": "CARACTERÍSTICAS ESPIRITUAIS DISTINTIVAS",
      "linhas": [
        "- Mestre da liberação bodhisattva \"domínio incessante\"",
        "- Praticante da base para realizar onisciência",
        "- Praticante de ascetismo extremo (cinco calores)",
        "- Poder de transformar seres apenas através de sua disciplina feroz",
        "- Capacidade de abalar montanhas Meru com o olhar",
        "- Luz dos fogos alcança até o inferno Avīci",
        "",
        "PODER TRANSFORMATIVO DA PRÁTICA",
        "",
        "Efeitos em seres celestiais durante a prática dos cinco calores:",
        "",
        "**Brahmās Poderosos:**",
        "- Cessaram prazer em seus estados",
        "- Perderam gosto por dhyāna",
        "- Abandonaram visões errôneas",
        "- Desenvolveram grande amor e compaixão",
        "- Obtiveram aspiração inabalável à iluminação",
        "",
        "**Māras:**",
        "- Radiância ofuscou suas residências e posses",
        "- Cessaram prazer em suas moradas",
        "- Mentes foram curadas",
        "- Desenvolveram aspiração à iluminação",
        "- Tornaram-se irreversíveis no caminho",
        "",
        "**Reis Devas Vaśavartin:**",
        "- Cessaram deleite em residências",
        "- Ganharam controle sobre próprias mentes",
        "- Obtiveram poder sobre kleśas",
        "- Adquiriram poder de renascer onde desejam",
        "- Ganharam poder sobre estados meditativos",
        "",
        "**Reis Devas Sunirmita:**",
        "- Luz purificou e iluminou palácios aéreos",
        "- Cessaram deleite em apsarases",
        "- Perderam prazer no bem-aventurança do desejo",
        "- Mentes purificadas e iluminadas",
        "- Obtiveram conhecimento das dez forças",
        "",
        "**Reis Devas Saṃtuṣita:**",
        "- Cessaram deleite em residências",
        "- Não mais dependentes de objetos sensoriais",
        "- Mentes ganharam contentamento",
        "- Criaram raízes de mérito",
        "- Desenvolveram aspiração à iluminação",
        "",
        "**Reis Devas Suyāma:**",
        "- Cessaram deleite em canções divinas",
        "- Afastaram-se de todos os prazeres dos desejos",
        "- Atingiram todo o Buddhadharma",
        "",
        "**Śakras (Senhores dos Devas):**",
        "- Cessaram deleite em palácios e parques",
        "- Abandonaram música divina e canções",
        "- Renunciaram a todos os prazeres dos desejos",
        "- Desenvolveram aspiração à iluminação suprema",
        "",
        "**Nāgas (Airāvata, Nanda, Upananda):**",
        "- Luz eliminou chuvas de areia e medo dos garuḍas",
        "- Pacificou raiva e refrescou corpos",
        "- Repudiaram caminhos malignos dos nāgas",
        "- Confessaram transgressões",
        "- Estabelecidos na onisciência",
        "",
        "**Senhores Yakṣa:**",
        "- Desenvolveram mente amorosa em relação aos humanos",
        "- Yakṣas, rākṣasas e kumbhāṇḍas cessaram violência",
        "- Corpos e mentes tornaram-se bem-aventurados",
        "- Multidão de seres desenvolveu aspiração à iluminação",
        "",
        "**Senhores Gandharva:**",
        "- Luz iluminou suas moradas",
        "- Experienciaram bem-aventurança inconcebível",
        "- Progrediram irreversivelmente à iluminação",
        "",
        "**Senhores Asura:**",
        "- Mundo asura tremeu com oceanos e montanhas",
        "- Arrogância e orgulho foram dominados",
        "- Abandonaram toda decepção",
        "- Estabelecidos na natureza verdadeira dos fenômenos",
        "",
        "**Senhores Garuḍa:**",
        "- Manifestaram-se como jovens brâmanes belos",
        "- Ficaram assustados e consternados",
        "- Praticaram grande amor e compaixão",
        "- Aplicaram-se a salvar seres no pântano do desejo",
        "",
        "**Senhores Kinnara:**",
        "- Sons de \"Buda\", \"Dharma\", \"Saṅgha\" emergiram de suas árvores",
        "- Instrumentos musicais ressoaram nomes de Tathāgatas",
        "- Escutaram sobre atividades bodhisattva em mundos infinitos",
        "- Experimentaram bem-aventurança através dos sons sagrados",
        "",
        "**Devas do Reino do Desejo:**",
        "- Luz alcançou até inferno Avīci",
        "- Extinguiu sofrimentos de seres nos infernos",
        "- Renunciaram ao deleite nos desejos",
        "- Oraram pela iluminação de seres ilimitados",
        "",
        "TESTE DE FÉ E CONFIANÇA",
        "",
        "Desafio inicial:",
        "- Ordena Sudhana a subir montanha por caminho de navalhas",
        "- Instrui saltar no fogo",
        "- Sudhana inicialmente duvida se é māra ou kalyāṇamitra",
        "- Dez mil seres celestiais testemunham em favor do brâmane",
        "",
        "Resultado do teste:",
        "- Sudhana obedece e sobe o caminho de navalhas",
        "- Pula no fogo e experimenta bem-aventurança",
        "- Atinge samādhi \"completamente estável\" subindo",
        "- Atinge samādhi \"percebendo bem-aventurança da paz\" no fogo",
        "- Descobre que fogo e navalhas são bem-aventurados ao toque",
        "",
        "LIBERAÇÃO \"DOMÍNIO INCESSANTE\"",
        "",
        "Características da liberação:",
        "- Transforma aparentes obstáculos em bênçãos",
        "- Converte experiências dolorosas em bem-aventurança",
        "- Permite prática ascética que beneficia incontáveis seres",
        "- Demonstra poder da mente sobre percepções físicas",
        "- Ensina que verdadeiros obstáculos são mentais, não físicos",
        "",
        "ENSINAMENTO SOBRE OBEDIÊNCIA AO GURU",
        "",
        "Verso recitado a Sudhana:",
        "\"O bodhisattva que segue com sucesso as instruções",
        "E que tem atenção para não desobedecer as palavras do guru",
        "Realizará com sucesso todos os objetivos e",
        "Atingirá com sucesso a sabedoria da budidade, iluminado sob a Árvore Bodhi\""
      ],
      "conteudo": "- Mestre da liberação bodhisattva \"domínio incessante\"\n- Praticante da base para realizar onisciência\n- Praticante de ascetismo extremo (cinco calores)\n- Poder de transformar seres apenas através de sua disciplina feroz\n- Capacidade de abalar montanhas Meru com o olhar\n- Luz dos fogos alcança até o inferno Avīci\n\nPODER TRANSFORMATIVO DA PRÁTICA\n\nEfeitos em seres celestiais durante a prática dos cinco calores:\n\n**Brahmās Poderosos:**\n- Cessaram prazer em seus estados\n- Perderam gosto por dhyāna\n- Abandonaram visões errôneas\n- Desenvolveram grande amor e compaixão\n- Obtiveram aspiração inabalável à iluminação\n\n**Māras:**\n- Radiância ofuscou suas residências e posses\n- Cessaram prazer em suas moradas\n- Mentes foram curadas\n- Desenvolveram aspiração à iluminação\n- Tornaram-se irreversíveis no caminho\n\n**Reis Devas Vaśavartin:**\n- Cessaram deleite em residências\n- Ganharam controle sobre próprias mentes\n- Obtiveram poder sobre kleśas\n- Adquiriram poder de renascer onde desejam\n- Ganharam poder sobre estados meditativos\n\n**Reis Devas Sunirmita:**\n- Luz purificou e iluminou palácios aéreos\n- Cessaram deleite em apsarases\n- Perderam prazer no bem-aventurança do desejo\n- Mentes purificadas e iluminadas\n- Obtiveram conhecimento das dez forças\n\n**Reis Devas Saṃtuṣita:**\n- Cessaram deleite em residências\n- Não mais dependentes de objetos sensoriais\n- Mentes ganharam contentamento\n- Criaram raízes de mérito\n- Desenvolveram aspiração à iluminação\n\n**Reis Devas Suyāma:**\n- Cessaram deleite em canções divinas\n- Afastaram-se de todos os prazeres dos desejos\n- Atingiram todo o Buddhadharma\n\n**Śakras (Senhores dos Devas):**\n- Cessaram deleite em palácios e parques\n- Abandonaram música divina e canções\n- Renunciaram a todos os prazeres dos desejos\n- Desenvolveram aspiração à iluminação suprema\n\n**Nāgas (Airāvata, Nanda, Upananda):**\n- Luz eliminou chuvas de areia e medo dos garuḍas\n- Pacificou raiva e refrescou corpos\n- Repudiaram caminhos malignos dos nāgas\n- Confessaram transgressões\n- Estabelecidos na onisciência\n\n**Senhores Yakṣa:**\n- Desenvolveram mente amorosa em relação aos humanos\n- Yakṣas, rākṣasas e kumbhāṇḍas cessaram violência\n- Corpos e mentes tornaram-se bem-aventurados\n- Multidão de seres desenvolveu aspiração à iluminação\n\n**Senhores Gandharva:**\n- Luz iluminou suas moradas\n- Experienciaram bem-aventurança inconcebível\n- Progrediram irreversivelmente à iluminação\n\n**Senhores Asura:**\n- Mundo asura tremeu com oceanos e montanhas\n- Arrogância e orgulho foram dominados\n- Abandonaram toda decepção\n- Estabelecidos na natureza verdadeira dos fenômenos\n\n**Senhores Garuḍa:**\n- Manifestaram-se como jovens brâmanes belos\n- Ficaram assustados e consternados\n- Praticaram grande amor e compaixão\n- Aplicaram-se a salvar seres no pântano do desejo\n\n**Senhores Kinnara:**\n- Sons de \"Buda\", \"Dharma\", \"Saṅgha\" emergiram de suas árvores\n- Instrumentos musicais ressoaram nomes de Tathāgatas\n- Escutaram sobre atividades bodhisattva em mundos infinitos\n- Experimentaram bem-aventurança através dos sons sagrados\n\n**Devas do Reino do Desejo:**\n- Luz alcançou até inferno Avīci\n- Extinguiu sofrimentos de seres nos infernos\n- Renunciaram ao deleite nos desejos\n- Oraram pela iluminação de seres ilimitados\n\nTESTE DE FÉ E CONFIANÇA\n\nDesafio inicial:\n- Ordena Sudhana a subir montanha por caminho de navalhas\n- Instrui saltar no fogo\n- Sudhana inicialmente duvida se é māra ou kalyāṇamitra\n- Dez mil seres celestiais testemunham em favor do brâmane\n\nResultado do teste:\n- Sudhana obedece e sobe o caminho de navalhas\n- Pula no fogo e experimenta bem-aventurança\n- Atinge samādhi \"completamente estável\" subindo\n- Atinge samādhi \"percebendo bem-aventurança da paz\" no fogo\n- Descobre que fogo e navalhas são bem-aventurados ao toque\n\nLIBERAÇÃO \"DOMÍNIO INCESSANTE\"\n\nCaracterísticas da liberação:\n- Transforma aparentes obstáculos em bênçãos\n- Converte experiências dolorosas em bem-aventurança\n- Permite prática ascética que beneficia incontáveis seres\n- Demonstra poder da mente sobre percepções físicas\n- Ensina que verdadeiros obstáculos são mentais, não físicos\n\nENSINAMENTO SOBRE OBEDIÊNCIA AO GURU\n\nVerso recitado a Sudhana:\n\"O bodhisattva que segue com sucesso as instruções\nE que tem atenção para não desobedecer as palavras do guru\nRealizará com sucesso todos os objetivos e\nAtingirá com sucesso a sabedoria da budidade, iluminado sob a Árvore Bodhi\""
    },
    {
      "titulo": "LOCALIZAÇÃO E CONTEXTO",
      "linhas": [
        "- Pratica na terra de Īṣāṇa",
        "- Realiza ascetismo em local com precipícios e fogos montanhosos",
        "- Centro de transformação para seres de todos os reinos",
        "- Local de teste definitivo de fé na orientação espiritual",
        "- Demonstração de que aparências podem enganar no caminho espiritual"
      ],
      "conteudo": "- Pratica na terra de Īṣāṇa\n- Realiza ascetismo em local com precipícios e fogos montanhosos\n- Centro de transformação para seres de todos os reinos\n- Local de teste definitivo de fé na orientação espiritual\n- Demonstração de que aparências podem enganar no caminho espiritual"
    }
  ],
  "metadados": {
    "total_linhas": 170,
    "total_caracteres": 5546,
    "secoes_encontradas": 5,
    "dados_estruturados_extraidos": 4
  },
  "arquivo_origem": "Jayosmayatana_Perfil.txt",
  "caminho_completo": "C:\\Users\\rouxy\\TECHNOSUTRA1\\technosutra\\characters\\Jayosmayatana_Perfil.txt"
}