{
  "titulo_principal": "Título não identificado",
  "conteudo_completo": "NOME DO PERSONAGEM\n\nMaitrayaṇī\n\nINFORMAÇÕES BÁSICAS\n\nNome e Tradução: Maitrayaṇī (Relacionada à Bondade Amorosa)\nTipo: Filha do Rei Siṃhaketu\nLocalização: Palácio Vairocana garbha na cidade de Siṃha vijṛmbhita\nStatus: Mestre do ensino \"portal à perfeição da sabedoria chamado exibição completa\"\n\nDESCRIÇÃO FÍSICA\nAparência Visual\n\nCor do Corpo: Pele dourada\nCabelo: Cabelo preto profundo\nOlhos: Olhos pretos profundos\nBeleza Geral: Presença majestosa e graciosa\nAdornos: \n- Sentada em um trono com pernas de sândalo uragasāra\n- Decorada com uma rede de fios de ouro\nVestimentas: Almofada de material divino\n\nCARACTERÍSTICAS ESPIRITUAIS DISTINTIVAS\n\n- Mestre do \"portal à perfeição da sabedoria chamado exibição completa\"\n- Conhecimento obtido de tathāgatas tão numerosos quanto os grãos de areia em 360 milhões de Rios Ganges\n- Cada objeto em seu palácio reflete ensinamentos e atividades dos tathāgatas\n\nENSINAMENTOS SOBRE A PERFEIÇÃO DA SABEDORIA\n\nEm cada objeto de percepção no Palácio Vairocana garbha:\n- Imagens dos tathāgatas iniciando aspiração à iluminação, conduta e oração\n- Exibições da manifestação do estado de buda, giro da roda do Dharma, demonstração de entrada no nirvāṇa\n\nPoder de Retenção \"Portais Completos\"\n- Inúmeros portais do Dharma incluídos e manifestados\n- Abrange portais para reinos dos budas, passado, futuro, presente, mérito, sabedoria, oração, karma, samādhi, mente, compaixão, amor e paz\n- Inclui portais para aspiração, conduta, e formas da sábia prática bodhisattva\n\nLOCALIZAÇÃO E CONTEXTO\n\n- Reside no magnífico Palácio Vairocana garbha\n- Palácio adornado com chão de cristal, pilares de berilo, paredes de diamantes\n- Decorado com pináculos de ouro maciço e joias preciosas\n- Visitada por multidões que buscam ensinamentos do Dharma\n\nFILOSOFIA DE ENSINAMENTO\n\n- Sabedoria é um portal para múltiplos mundos e experiências\n- Cada percepção pode refletir o vasto universo dos ensinamentos dos budas\n- Não se engaja com qualidades mundanas, mas transcende-as\n\nSÍNTESE DESCRITIVA, PEQUENO 1 PARÁGRAFO}\n\nMaitrayaṇī é uma figura majestosa com pele dourada e cabelos pretos profundos que refletem a sabedoria bucólica. Sentada graciosamente em um trono adornado de ouro, ela emana uma presença de paz e sabedoria. Seu olhar é profundo, como se contivesse os segredos do universo, enquanto cada movimento seu é carregado de graciosidade divina, refletida nas joias preciosas que adornam seu reinado espiritual.\n",
  "dados_estruturados": {
    "informacoes_basicas": {
      "nome_e_traducao": "Maitrayaṇī (Relacionada à Bondade Amorosa)",
      "tipo": "Filha do Rei Siṃhaketu",
      "localizacao": "Palácio Vairocana garbha na cidade de Siṃha vijṛmbhita",
      "status": "Mestre do ensino \"portal à perfeição da sabedoria chamado exibição completa\""
    },
    "descricao_fisica": {
      "cor_do_corpo": "Pele dourada",
      "cabelo": "Cabelo preto profundo",
      "olhos": "Olhos pretos profundos",
      "beleza_geral": "Presença majestosa e graciosa",
      "adornos": "",
      "vestimentas": "Almofada de material divino"
    },
    "caracteristicas_espirituais": [
      "- Mestre do \"portal à perfeição da sabedoria chamado exibição completa\"",
      "- Conhecimento obtido de tathāgatas tão numerosos quanto os grãos de areia em 360 milhões de Rios Ganges",
      "- Cada objeto em seu palácio reflete ensinamentos e atividades dos tathāgatas",
      "",
      "ENSINAMENTOS SOBRE A PERFEIÇÃO DA SABEDORIA",
      "",
      "Em cada objeto de percepção no Palácio Vairocana garbha:",
      "- Imagens dos tathāgatas iniciando aspiração à iluminação, conduta e oração",
      "- Exibições da manifestação do estado de buda, giro da roda do Dharma, demonstração de entrada no nirvāṇa",
      "",
      "Poder de Retenção \"Portais Completos\"",
      "- Inúmeros portais do Dharma incluídos e manifestados",
      "- Abrange portais para reinos dos budas, passado, futuro, presente, mérito, sabedoria, oração, karma, samādhi, mente, compaixão, amor e paz",
      "- Inclui portais para aspiração, conduta, e formas da sábia prática bodhisattva"
    ],
    "localizacao_contexto": "- Reside no magnífico Palácio Vairocana garbha\n- Palácio adornado com chão de cristal, pilares de berilo, paredes de diamantes\n- Decorado com pináculos de ouro maciço e joias preciosas\n- Visitada por multidões que buscam ensinamentos do Dharma\n\nFILOSOFIA DE ENSINAMENTO\n\n- Sabedoria é um portal para múltiplos mundos e experiências\n- Cada percepção pode refletir o vasto universo dos ensinamentos dos budas\n- Não se engaja com qualidades mundanas, mas transcende-as"
  },
  "secoes_organizadas": [
    {
      "titulo": "NOME DO PERSONAGEM",
      "linhas": [
        "Maitrayaṇī"
      ],
      "conteudo": "Maitrayaṇī"
    },
    {
      "titulo": "INFORMAÇÕES BÁSICAS",
      "linhas": [
        "Nome e Tradução: Maitrayaṇī (Relacionada à Bondade Amorosa)",
        "Tipo: Filha do Rei Siṃhaketu",
        "Localização: Palácio Vairocana garbha na cidade de Siṃha vijṛmbhita",
        "Status: Mestre do ensino \"portal à perfeição da sabedoria chamado exibição completa\""
      ],
      "conteudo": "Nome e Tradução: Maitrayaṇī (Relacionada à Bondade Amorosa)\nTipo: Filha do Rei Siṃhaketu\nLocalização: Palácio Vairocana garbha na cidade de Siṃha vijṛmbhita\nStatus: Mestre do ensino \"portal à perfeição da sabedoria chamado exibição completa\""
    },
    {
      "titulo": "DESCRIÇÃO FÍSICA",
      "linhas": [
        "Aparência Visual",
        "",
        "Cor do Corpo: Pele dourada",
        "Cabelo: Cabelo preto profundo",
        "Olhos: Olhos pretos profundos",
        "Beleza Geral: Presença majestosa e graciosa",
        "Adornos: ",
        "- Sentada em um trono com pernas de sândalo uragasāra",
        "- Decorada com uma rede de fios de ouro",
        "Vestimentas: Almofada de material divino"
      ],
      "conteudo": "Aparência Visual\n\nCor do Corpo: Pele dourada\nCabelo: Cabelo preto profundo\nOlhos: Olhos pretos profundos\nBeleza Geral: Presença majestosa e graciosa\nAdornos: \n- Sentada em um trono com pernas de sândalo uragasāra\n- Decorada com uma rede de fios de ouro\nVestimentas: Almofada de material divino"
    },
    {
      "titulo": "CARACTERÍSTICAS ESPIRITUAIS DISTINTIVAS",
      "linhas": [
        "- Mestre do \"portal à perfeição da sabedoria chamado exibição completa\"",
        "- Conhecimento obtido de tathāgatas tão numerosos quanto os grãos de areia em 360 milhões de Rios Ganges",
        "- Cada objeto em seu palácio reflete ensinamentos e atividades dos tathāgatas",
        "",
        "ENSINAMENTOS SOBRE A PERFEIÇÃO DA SABEDORIA",
        "",
        "Em cada objeto de percepção no Palácio Vairocana garbha:",
        "- Imagens dos tathāgatas iniciando aspiração à iluminação, conduta e oração",
        "- Exibições da manifestação do estado de buda, giro da roda do Dharma, demonstração de entrada no nirvāṇa",
        "",
        "Poder de Retenção \"Portais Completos\"",
        "- Inúmeros portais do Dharma incluídos e manifestados",
        "- Abrange portais para reinos dos budas, passado, futuro, presente, mérito, sabedoria, oração, karma, samādhi, mente, compaixão, amor e paz",
        "- Inclui portais para aspiração, conduta, e formas da sábia prática bodhisattva"
      ],
      "conteudo": "- Mestre do \"portal à perfeição da sabedoria chamado exibição completa\"\n- Conhecimento obtido de tathāgatas tão numerosos quanto os grãos de areia em 360 milhões de Rios Ganges\n- Cada objeto em seu palácio reflete ensinamentos e atividades dos tathāgatas\n\nENSINAMENTOS SOBRE A PERFEIÇÃO DA SABEDORIA\n\nEm cada objeto de percepção no Palácio Vairocana garbha:\n- Imagens dos tathāgatas iniciando aspiração à iluminação, conduta e oração\n- Exibições da manifestação do estado de buda, giro da roda do Dharma, demonstração de entrada no nirvāṇa\n\nPoder de Retenção \"Portais Completos\"\n- Inúmeros portais do Dharma incluídos e manifestados\n- Abrange portais para reinos dos budas, passado, futuro, presente, mérito, sabedoria, oração, karma, samādhi, mente, compaixão, amor e paz\n- Inclui portais para aspiração, conduta, e formas da sábia prática bodhisattva"
    },
    {
      "titulo": "LOCALIZAÇÃO E CONTEXTO",
      "linhas": [
        "- Reside no magnífico Palácio Vairocana garbha",
        "- Palácio adornado com chão de cristal, pilares de berilo, paredes de diamantes",
        "- Decorado com pináculos de ouro maciço e joias preciosas",
        "- Visitada por multidões que buscam ensinamentos do Dharma",
        "",
        "FILOSOFIA DE ENSINAMENTO",
        "",
        "- Sabedoria é um portal para múltiplos mundos e experiências",
        "- Cada percepção pode refletir o vasto universo dos ensinamentos dos budas",
        "- Não se engaja com qualidades mundanas, mas transcende-as"
      ],
      "conteudo": "- Reside no magnífico Palácio Vairocana garbha\n- Palácio adornado com chão de cristal, pilares de berilo, paredes de diamantes\n- Decorado com pináculos de ouro maciço e joias preciosas\n- Visitada por multidões que buscam ensinamentos do Dharma\n\nFILOSOFIA DE ENSINAMENTO\n\n- Sabedoria é um portal para múltiplos mundos e experiências\n- Cada percepção pode refletir o vasto universo dos ensinamentos dos budas\n- Não se engaja com qualidades mundanas, mas transcende-as"
    },
    {
      "titulo": "SÍNTESE DESCRITIVA, PEQUENO 1 PARÁGRAFO}",
      "linhas": [
        "Maitrayaṇī é uma figura majestosa com pele dourada e cabelos pretos profundos que refletem a sabedoria bucólica. Sentada graciosamente em um trono adornado de ouro, ela emana uma presença de paz e sabedoria. Seu olhar é profundo, como se contivesse os segredos do universo, enquanto cada movimento seu é carregado de graciosidade divina, refletida nas joias preciosas que adornam seu reinado espiritual."
      ],
      "conteudo": "Maitrayaṇī é uma figura majestosa com pele dourada e cabelos pretos profundos que refletem a sabedoria bucólica. Sentada graciosamente em um trono adornado de ouro, ela emana uma presença de paz e sabedoria. Seu olhar é profundo, como se contivesse os segredos do universo, enquanto cada movimento seu é carregado de graciosidade divina, refletida nas joias preciosas que adornam seu reinado espiritual."
    }
  ],
  "metadados": {
    "total_linhas": 57,
    "total_caracteres": 2440,
    "secoes_encontradas": 6,
    "dados_estruturados_extraidos": 4
  },
  "arquivo_origem": "Maitrayani_Perfil.txt",
  "caminho_completo": "C:\\Users\\rouxy\\TECHNOSUTRA1\\technosutra\\characters\\Maitrayani_Perfil.txt"
}