{
  "titulo_principal": "Título não identificado",
  "conteudo_completo": "NOME DO PERSONAGEM\n\nMegha (O Dravidiano)\n\nINFORMAÇÕES BÁSICAS\n\nNome e Tradução: Megha (Nuvem) - O Dravidiano\nTipo: Dravidiano leigo (upāsaka)\nLocalização: Vajrapura na região de Draviḍa\nStatus: Mestre do poder de retenção de Sarasvatī, professor de linguagens divinas\n\nDESCRIÇÃO FÍSICA\nAparência Visual\n\nCor do Corpo: Não especificado diretamente\nCabelo: Não especificado\nOlhos: Não especificado fisicamente\nBeleza Geral: Não descrita em detalhes físicos\nAdornos: Não especificado\nVestimentas: Não especificado diretamente (presumivelmente roupas de um homem próspero)\n\nCARACTERÍSTICAS ESPIRITUAIS DISTINTIVAS\n\n- Mestre do \"poder de retenção de Sarasvatī\"\n- Conhecedor de todas as linguagens divinas e mundanas\n- Capaz de ensinar \"A Exibição da Roda Giratória de Sílabas\"\n- Emissor de raios de luz pela boca durante ensinamentos\n- Conhecimento instantâneo de linguagens em múltiplos reinos mundiais\n- Compreensão dos oceanos da fala dos Tathāgatas dos três tempos\n\nLINGUAGENS E COMUNICAÇÃO\n\n- Linguagens divinas dos devas\n- Linguagens dos nāgas, yakṣas, gandharvas, asuras, garuḍas\n- Linguagens dos kinnaras, mahoragas, humanos e não-humanos\n- Linguagem Brahmakāyika dos devas Brahmakāyika\n- Sinais e linguagens dos seres renascidos como animais\n- Linguagens dos seres nos infernos\n- Linguagens dos seres no reino de Yama\n- Linguagens dos āryas e não-āryas\n- Palavras e definições dos bodhisattvas\n\nMANIFESTAÇÕES DURANTE O ENSINO\n\n- Senta-se em um trono de leão para ensinar o Dharma\n- Emite massa de raios de luz da boca\n- Os raios se espalham por bilhões de mundos\n- Seres iluminados pelos raios vêm à sua presença\n- Abençoa os pensamentos dos seres\n- Causa irreversibilidade no progresso para a iluminação\n\nATOS DE REVERÊNCIA\n\n- Levanta-se do trono e se prostra diante de Sudhana\n- Espalha flores douradas\n- Oferece joias preciosas e pó de sândalo supremo\n- Drapa centenas de milhares de tecidos coloridos\n- Oferece flores perfumadas de várias cores\n- Demonstra respeito, honra e veneração\n\nLOCALIZAÇÃO E CONTEXTO\n\n- Encontrado em um dos pátios da cidade Vajrapura\n- Sentado em trono de leão ensinando cerca de 10.000 seres\n- Localizado na região de Draviḍa\n- Permanece ensinando o Dharma continuamente\n\nCAPACIDADES EXTRAORDINÁRIAS\n\n- Percepção instantânea de aspectos das vozes dos Tathāgatas\n- Compreensão dos oceanos da fala de todos os seres\n- Conhecimento de termos, definições e nomes em incontáveis reinos\n- Entrada em oceanos de várias categorias linguísticas e conceituais\n",
  "dados_estruturados": {
    "informacoes_basicas": {
      "nome_e_traducao": "Megha (Nuvem) - O Dravidiano",
      "tipo": "Dravidiano leigo (upāsaka)",
      "localizacao": "Vajrapura na região de Draviḍa",
      "status": "Mestre do poder de retenção de Sarasvatī, professor de linguagens divinas"
    },
    "descricao_fisica": {
      "cor_do_corpo": "Não especificado diretamente",
      "cabelo": "Não especificado",
      "olhos": "Não especificado fisicamente",
      "beleza_geral": "Não descrita em detalhes físicos",
      "adornos": "Não especificado",
      "vestimentas": "Não especificado diretamente (presumivelmente roupas de um homem próspero)"
    },
    "caracteristicas_espirituais": [
      "- Mestre do \"poder de retenção de Sarasvatī\"",
      "- Conhecedor de todas as linguagens divinas e mundanas",
      "- Capaz de ensinar \"A Exibição da Roda Giratória de Sílabas\"",
      "- Emissor de raios de luz pela boca durante ensinamentos",
      "- Conhecimento instantâneo de linguagens em múltiplos reinos mundiais",
      "- Compreensão dos oceanos da fala dos Tathāgatas dos três tempos",
      "",
      "LINGUAGENS E COMUNICAÇÃO",
      "",
      "- Linguagens divinas dos devas",
      "- Linguagens dos nāgas, yakṣas, gandharvas, asuras, garuḍas",
      "- Linguagens dos kinnaras, mahoragas, humanos e não-humanos",
      "- Linguagem Brahmakāyika dos devas Brahmakāyika",
      "- Sinais e linguagens dos seres renascidos como animais",
      "- Linguagens dos seres nos infernos",
      "- Linguagens dos seres no reino de Yama",
      "- Linguagens dos āryas e não-āryas",
      "- Palavras e definições dos bodhisattvas",
      "",
      "MANIFESTAÇÕES DURANTE O ENSINO",
      "",
      "- Senta-se em um trono de leão para ensinar o Dharma",
      "- Emite massa de raios de luz da boca",
      "- Os raios se espalham por bilhões de mundos",
      "- Seres iluminados pelos raios vêm à sua presença",
      "- Abençoa os pensamentos dos seres",
      "- Causa irreversibilidade no progresso para a iluminação",
      "",
      "ATOS DE REVERÊNCIA",
      "",
      "- Levanta-se do trono e se prostra diante de Sudhana",
      "- Espalha flores douradas",
      "- Oferece joias preciosas e pó de sândalo supremo",
      "- Drapa centenas de milhares de tecidos coloridos",
      "- Oferece flores perfumadas de várias cores",
      "- Demonstra respeito, honra e veneração"
    ],
    "localizacao_contexto": "- Encontrado em um dos pátios da cidade Vajrapura\n- Sentado em trono de leão ensinando cerca de 10.000 seres\n- Localizado na região de Draviḍa\n- Permanece ensinando o Dharma continuamente\n\nCAPACIDADES EXTRAORDINÁRIAS\n\n- Percepção instantânea de aspectos das vozes dos Tathāgatas\n- Compreensão dos oceanos da fala de todos os seres\n- Conhecimento de termos, definições e nomes em incontáveis reinos\n- Entrada em oceanos de várias categorias linguísticas e conceituais"
  },
  "secoes_organizadas": [
    {
      "titulo": "NOME DO PERSONAGEM",
      "linhas": [
        "Megha (O Dravidiano)"
      ],
      "conteudo": "Megha (O Dravidiano)"
    },
    {
      "titulo": "INFORMAÇÕES BÁSICAS",
      "linhas": [
        "Nome e Tradução: Megha (Nuvem) - O Dravidiano",
        "Tipo: Dravidiano leigo (upāsaka)",
        "Localização: Vajrapura na região de Draviḍa",
        "Status: Mestre do poder de retenção de Sarasvatī, professor de linguagens divinas"
      ],
      "conteudo": "Nome e Tradução: Megha (Nuvem) - O Dravidiano\nTipo: Dravidiano leigo (upāsaka)\nLocalização: Vajrapura na região de Draviḍa\nStatus: Mestre do poder de retenção de Sarasvatī, professor de linguagens divinas"
    },
    {
      "titulo": "DESCRIÇÃO FÍSICA",
      "linhas": [
        "Aparência Visual",
        "",
        "Cor do Corpo: Não especificado diretamente",
        "Cabelo: Não especificado",
        "Olhos: Não especificado fisicamente",
        "Beleza Geral: Não descrita em detalhes físicos",
        "Adornos: Não especificado",
        "Vestimentas: Não especificado diretamente (presumivelmente roupas de um homem próspero)"
      ],
      "conteudo": "Aparência Visual\n\nCor do Corpo: Não especificado diretamente\nCabelo: Não especificado\nOlhos: Não especificado fisicamente\nBeleza Geral: Não descrita em detalhes físicos\nAdornos: Não especificado\nVestimentas: Não especificado diretamente (presumivelmente roupas de um homem próspero)"
    },
    {
      "titulo": "CARACTERÍSTICAS ESPIRITUAIS DISTINTIVAS",
      "linhas": [
        "- Mestre do \"poder de retenção de Sarasvatī\"",
        "- Conhecedor de todas as linguagens divinas e mundanas",
        "- Capaz de ensinar \"A Exibição da Roda Giratória de Sílabas\"",
        "- Emissor de raios de luz pela boca durante ensinamentos",
        "- Conhecimento instantâneo de linguagens em múltiplos reinos mundiais",
        "- Compreensão dos oceanos da fala dos Tathāgatas dos três tempos",
        "",
        "LINGUAGENS E COMUNICAÇÃO",
        "",
        "- Linguagens divinas dos devas",
        "- Linguagens dos nāgas, yakṣas, gandharvas, asuras, garuḍas",
        "- Linguagens dos kinnaras, mahoragas, humanos e não-humanos",
        "- Linguagem Brahmakāyika dos devas Brahmakāyika",
        "- Sinais e linguagens dos seres renascidos como animais",
        "- Linguagens dos seres nos infernos",
        "- Linguagens dos seres no reino de Yama",
        "- Linguagens dos āryas e não-āryas",
        "- Palavras e definições dos bodhisattvas",
        "",
        "MANIFESTAÇÕES DURANTE O ENSINO",
        "",
        "- Senta-se em um trono de leão para ensinar o Dharma",
        "- Emite massa de raios de luz da boca",
        "- Os raios se espalham por bilhões de mundos",
        "- Seres iluminados pelos raios vêm à sua presença",
        "- Abençoa os pensamentos dos seres",
        "- Causa irreversibilidade no progresso para a iluminação",
        "",
        "ATOS DE REVERÊNCIA",
        "",
        "- Levanta-se do trono e se prostra diante de Sudhana",
        "- Espalha flores douradas",
        "- Oferece joias preciosas e pó de sândalo supremo",
        "- Drapa centenas de milhares de tecidos coloridos",
        "- Oferece flores perfumadas de várias cores",
        "- Demonstra respeito, honra e veneração"
      ],
      "conteudo": "- Mestre do \"poder de retenção de Sarasvatī\"\n- Conhecedor de todas as linguagens divinas e mundanas\n- Capaz de ensinar \"A Exibição da Roda Giratória de Sílabas\"\n- Emissor de raios de luz pela boca durante ensinamentos\n- Conhecimento instantâneo de linguagens em múltiplos reinos mundiais\n- Compreensão dos oceanos da fala dos Tathāgatas dos três tempos\n\nLINGUAGENS E COMUNICAÇÃO\n\n- Linguagens divinas dos devas\n- Linguagens dos nāgas, yakṣas, gandharvas, asuras, garuḍas\n- Linguagens dos kinnaras, mahoragas, humanos e não-humanos\n- Linguagem Brahmakāyika dos devas Brahmakāyika\n- Sinais e linguagens dos seres renascidos como animais\n- Linguagens dos seres nos infernos\n- Linguagens dos seres no reino de Yama\n- Linguagens dos āryas e não-āryas\n- Palavras e definições dos bodhisattvas\n\nMANIFESTAÇÕES DURANTE O ENSINO\n\n- Senta-se em um trono de leão para ensinar o Dharma\n- Emite massa de raios de luz da boca\n- Os raios se espalham por bilhões de mundos\n- Seres iluminados pelos raios vêm à sua presença\n- Abençoa os pensamentos dos seres\n- Causa irreversibilidade no progresso para a iluminação\n\nATOS DE REVERÊNCIA\n\n- Levanta-se do trono e se prostra diante de Sudhana\n- Espalha flores douradas\n- Oferece joias preciosas e pó de sândalo supremo\n- Drapa centenas de milhares de tecidos coloridos\n- Oferece flores perfumadas de várias cores\n- Demonstra respeito, honra e veneração"
    },
    {
      "titulo": "LOCALIZAÇÃO E CONTEXTO",
      "linhas": [
        "- Encontrado em um dos pátios da cidade Vajrapura",
        "- Sentado em trono de leão ensinando cerca de 10.000 seres",
        "- Localizado na região de Draviḍa",
        "- Permanece ensinando o Dharma continuamente",
        "",
        "CAPACIDADES EXTRAORDINÁRIAS",
        "",
        "- Percepção instantânea de aspectos das vozes dos Tathāgatas",
        "- Compreensão dos oceanos da fala de todos os seres",
        "- Conhecimento de termos, definições e nomes em incontáveis reinos",
        "- Entrada em oceanos de várias categorias linguísticas e conceituais"
      ],
      "conteudo": "- Encontrado em um dos pátios da cidade Vajrapura\n- Sentado em trono de leão ensinando cerca de 10.000 seres\n- Localizado na região de Draviḍa\n- Permanece ensinando o Dharma continuamente\n\nCAPACIDADES EXTRAORDINÁRIAS\n\n- Percepção instantânea de aspectos das vozes dos Tathāgatas\n- Compreensão dos oceanos da fala de todos os seres\n- Conhecimento de termos, definições e nomes em incontáveis reinos\n- Entrada em oceanos de várias categorias linguísticas e conceituais"
    }
  ],
  "metadados": {
    "total_linhas": 74,
    "total_caracteres": 2485,
    "secoes_encontradas": 5,
    "dados_estruturados_extraidos": 4
  },
  "arquivo_origem": "Megha_Dravidian_Perfil.txt",
  "caminho_completo": "C:\\Users\\rouxy\\TECHNOSUTRA1\\technosutra\\characters\\Megha_Dravidian_Perfil.txt"
}