{
  "titulo_principal": "Título não identificado",
  "conteudo_completo": "NOME DO PERSONAGEM\n\nMeghaśrī\n\nINFORMAÇÕES BÁSICAS\n\nNome e Tradução: Meghaśrī (Glória da Nuvem)\nTipo: Bhikṣu (Monge budista)\nLocalização: Montanha Sugrīva, na terra de Rāmāvarānta (região sul)\nStatus: Mestre em mindfulness dos Budas, ensinando bodhisattvas\n\nDESCRIÇÃO FÍSICA\nAparência Visual\n\nCor do Corpo: Não especificado diretamente\nCabelo: Não especificado\nOlhos: Dotado de \"olhos puros de sabedoria\" e \"olhos puros de fé\"\nBeleza Geral: Possui corpo puro e campo de visão completamente puro\nAdornos: Não especificado\nVestimentas: Vestes de bhikṣu (monge budista)\n\nCARACTERÍSTICAS ESPIRITUAIS DISTINTIVAS\n\n- Possui visão desobstruída em todas as direções\n- Capaz de ver incontáveis Tathāgatas simultaneamente\n- Mestre dos portais de mindfulness dos Budas\n- Dotado do poder de retenção das nuvens do Dharma\n- Possui iluminação através da luz da sabedoria\n- Campo de visão livre de todas as obscurações\n- Observação astuta e percepção clara\n- Habilidade de curvatura corporal hábil ao fazer reverências\n\nLOCALIZAÇÃO E CONTEXTO\n\n- Encontrado caminhando em um platô no cume de uma montanha\n- Reside na região montanhosa de Sugrīva\n- Acessível após sete dias de busca em diferentes direções da montanha\n",
  "dados_estruturados": {
    "informacoes_basicas": {
      "nome_e_traducao": "Meghaśrī (Glória da Nuvem)",
      "tipo": "Bhikṣu (Monge budista)",
      "localizacao": "Montanha Sugrīva, na terra de Rāmāvarānta (região sul)",
      "status": "Mestre em mindfulness dos Budas, ensinando bodhisattvas"
    },
    "descricao_fisica": {
      "cor_do_corpo": "Não especificado diretamente",
      "cabelo": "Não especificado",
      "olhos": "Dotado de \"olhos puros de sabedoria\" e \"olhos puros de fé\"",
      "beleza_geral": "Possui corpo puro e campo de visão completamente puro",
      "adornos": "Não especificado",
      "vestimentas": "Vestes de bhikṣu (monge budista)"
    },
    "caracteristicas_espirituais": [
      "- Possui visão desobstruída em todas as direções",
      "- Capaz de ver incontáveis Tathāgatas simultaneamente",
      "- Mestre dos portais de mindfulness dos Budas",
      "- Dotado do poder de retenção das nuvens do Dharma",
      "- Possui iluminação através da luz da sabedoria",
      "- Campo de visão livre de todas as obscurações",
      "- Observação astuta e percepção clara",
      "- Habilidade de curvatura corporal hábil ao fazer reverências"
    ],
    "localizacao_contexto": "- Encontrado caminhando em um platô no cume de uma montanha\n- Reside na região montanhosa de Sugrīva\n- Acessível após sete dias de busca em diferentes direções da montanha"
  },
  "secoes_organizadas": [
    {
      "titulo": "NOME DO PERSONAGEM",
      "linhas": [
        "Meghaśrī"
      ],
      "conteudo": "Meghaśrī"
    },
    {
      "titulo": "INFORMAÇÕES BÁSICAS",
      "linhas": [
        "Nome e Tradução: Meghaśrī (Glória da Nuvem)",
        "Tipo: Bhikṣu (Monge budista)",
        "Localização: Montanha Sugrīva, na terra de Rāmāvarānta (região sul)",
        "Status: Mestre em mindfulness dos Budas, ensinando bodhisattvas"
      ],
      "conteudo": "Nome e Tradução: Meghaśrī (Glória da Nuvem)\nTipo: Bhikṣu (Monge budista)\nLocalização: Montanha Sugrīva, na terra de Rāmāvarānta (região sul)\nStatus: Mestre em mindfulness dos Budas, ensinando bodhisattvas"
    },
    {
      "titulo": "DESCRIÇÃO FÍSICA",
      "linhas": [
        "Aparência Visual",
        "",
        "Cor do Corpo: Não especificado diretamente",
        "Cabelo: Não especificado",
        "Olhos: Dotado de \"olhos puros de sabedoria\" e \"olhos puros de fé\"",
        "Beleza Geral: Possui corpo puro e campo de visão completamente puro",
        "Adornos: Não especificado",
        "Vestimentas: Vestes de bhikṣu (monge budista)"
      ],
      "conteudo": "Aparência Visual\n\nCor do Corpo: Não especificado diretamente\nCabelo: Não especificado\nOlhos: Dotado de \"olhos puros de sabedoria\" e \"olhos puros de fé\"\nBeleza Geral: Possui corpo puro e campo de visão completamente puro\nAdornos: Não especificado\nVestimentas: Vestes de bhikṣu (monge budista)"
    },
    {
      "titulo": "CARACTERÍSTICAS ESPIRITUAIS DISTINTIVAS",
      "linhas": [
        "- Possui visão desobstruída em todas as direções",
        "- Capaz de ver incontáveis Tathāgatas simultaneamente",
        "- Mestre dos portais de mindfulness dos Budas",
        "- Dotado do poder de retenção das nuvens do Dharma",
        "- Possui iluminação através da luz da sabedoria",
        "- Campo de visão livre de todas as obscurações",
        "- Observação astuta e percepção clara",
        "- Habilidade de curvatura corporal hábil ao fazer reverências"
      ],
      "conteudo": "- Possui visão desobstruída em todas as direções\n- Capaz de ver incontáveis Tathāgatas simultaneamente\n- Mestre dos portais de mindfulness dos Budas\n- Dotado do poder de retenção das nuvens do Dharma\n- Possui iluminação através da luz da sabedoria\n- Campo de visão livre de todas as obscurações\n- Observação astuta e percepção clara\n- Habilidade de curvatura corporal hábil ao fazer reverências"
    },
    {
      "titulo": "LOCALIZAÇÃO E CONTEXTO",
      "linhas": [
        "- Encontrado caminhando em um platô no cume de uma montanha",
        "- Reside na região montanhosa de Sugrīva",
        "- Acessível após sete dias de busca em diferentes direções da montanha"
      ],
      "conteudo": "- Encontrado caminhando em um platô no cume de uma montanha\n- Reside na região montanhosa de Sugrīva\n- Acessível após sete dias de busca em diferentes direções da montanha"
    }
  ]
}