{
  "titulo_principal": "PERFIL DE PERSONAGEM - CAPÍTULO 49",
  "conteudo_completo": "═══════════════════════════════════════════════════════════════════════════════\n                            PERFIL DE PERSONAGEM - CAPÍTULO 49\n═══════════════════════════════════════════════════════════════════════════════\n\nMUKTĀSĀRA\n\nINFORMAÇÕES BÁSICAS\n\nNome e Tradução: Muktāsāra (मुक्तासार) - \"Essência de Liberação\" ou \"Essência do Infinito\"\nTipo: Ourives / Professor Espiritual\nLocalização: Cidade de Bharukaccha, região sul\nStatus: Ativo como mestre bodhisattva em liberação mental\n\nDESCRIÇÃO FÍSICA\nAparência Visual\n\nCor do Corpo: Não especificada no texto\nCabelo: Não especificado no texto\nOlhos: Não especificado no texto\nBeleza Geral: Não especificada, mas comunicativa de sabedoria e serenidade\nAdornos: Provavelmente adornos associados à sua profissão de ourives\nVestimentas: Não especificadas, mas apropriadas para um artesão culto\n\nCARACTERÍSTICAS ESPIRITUAIS DISTINTIVAS\n\n- Mestre de Liberação Bodhisattva \"Exibição de Memória Pura Sem Impedimentos\"\n- Buscador contínuo do Dharma aos pés de todos os tathāgatas\n- Especializado em memórias conectando muitos budas (tathāgatas)\n- Conhecedor da continuidade e pureza da memória espiritual\n- Humilde em reconhecer suas próprias limitações e deferência aos grandes mestres\n\nEXPERIÊNCIA MÍSTICA CENTRAL\n\nMuktāsāra alcançou a liberação espiritual através da \"Exibição de Memória Pura Sem Impedimentos\". \nIsso lhe permite participar constantemente de ensinamentos nos dez cantos do universo, \napresentando sabedoria fluida e continua entre muitos budas.\n\nA principal experiência mística é o acesso e a manutenção de memoria infalível relacionada \naos ensinamentos dos tathāgatas, transcendendo tempo e espaço convencional.\n\nLOCALIZAÇÃO E CONTEXTO\n\nResidente da cidade de Bharukaccha na região sul, Muktāsāra representa o arquétipo do \nourives iluminado. Ele une suas habilidades artesanais com profundidade espiritual, \ndemonstrando que profissão e aperfeiçoamento espiritual podem andar juntos.\n\nANÁLISE ESPECIAL\n\nEste capítulo introduz um mestre que incorpora o equilíbrio entre habilidade mundana \ne sabedoria espiritual. Muktāsāra exemplifica como o talento profissional pode ser \nintegrado à prática Bodhisattva para criar uma vida de verdadeira realização.\n\nSeus ensinamentos refletem a importância do \"leão intrépido\", aqueles bodhisattvas que \ngarantem grande mérito e sabedoria além do que é óbvio para o mundo secular.\n\n{DESCRIÇÃO GENERATIVA: \nCreate a venerable and wise goldsmith named Muktāsāra, representing \"Essence of Liberation\". \nHe should appear as an enlightened artisan, with a calm and serene demeanor conveying \nboth craft mastery and spiritual depth. Include elements suggesting his profession, such as \nwearing tools or surrounded by jewels, with clothing suitable for a skilled and learned artisan. \nHis presence should exude a sense of infinite wisdom and timeless memory, with an expression \nthat reflects continuous learning and deep reflection. Blank background.}\n",
  "dados_estruturados": {
    "informacoes_basicas": {
      "nome_e_traducao": "Muktāsāra (मुक्तासार) - \"Essência de Liberação\" ou \"Essência do Infinito\"",
      "tipo": "Ourives / Professor Espiritual",
      "localizacao": "Cidade de Bharukaccha, região sul",
      "status": "Ativo como mestre bodhisattva em liberação mental"
    },
    "descricao_fisica": {
      "cor_do_corpo": "Não especificada no texto",
      "cabelo": "Não especificado no texto",
      "olhos": "Não especificado no texto",
      "beleza_geral": "Não especificada, mas comunicativa de sabedoria e serenidade",
      "adornos": "Provavelmente adornos associados à sua profissão de ourives",
      "vestimentas": "Não especificadas, mas apropriadas para um artesão culto"
    },
    "caracteristicas_espirituais": [
      "- Mestre de Liberação Bodhisattva \"Exibição de Memória Pura Sem Impedimentos\"",
      "- Buscador contínuo do Dharma aos pés de todos os tathāgatas",
      "- Especializado em memórias conectando muitos budas (tathāgatas)",
      "- Conhecedor da continuidade e pureza da memória espiritual",
      "- Humilde em reconhecer suas próprias limitações e deferência aos grandes mestres"
    ],
    "experiencia_mistica": "aos ensinamentos dos tathāgatas, transcendendo tempo e espaço convencional.",
    "localizacao_contexto": "Residente da cidade de Bharukaccha na região sul, Muktāsāra representa o arquétipo do \nourives iluminado. Ele une suas habilidades artesanais com profundidade espiritual, \ndemonstrando que profissão e aperfeiçoamento espiritual podem andar juntos.",
    "analise_especial": "Este capítulo introduz um mestre que incorpora o equilíbrio entre habilidade mundana \ne sabedoria espiritual. Muktāsāra exemplifica como o talento profissional pode ser \nintegrado à prática Bodhisattva para criar uma vida de verdadeira realização.\n\nSeus ensinamentos refletem a importância do \"leão intrépido\", aqueles bodhisattvas que \ngarantem grande mérito e sabedoria além do que é óbvio para o mundo secular.",
    "prompt_ia": "Create a venerable and wise goldsmith named Muktāsāra, representing \"Essence of Liberation\". \nHe should appear as an enlightened artisan, with a calm and serene demeanor conveying \nboth craft mastery and spiritual depth. Include elements suggesting his profession, such as \nwearing tools or surrounded by jewels, with clothing suitable for a skilled and learned artisan. \nHis presence should exude a sense of infinite wisdom and timeless memory, with an expression \nthat reflects continuous learning and deep reflection. Blank background."
  },
  "secoes_organizadas": [
    {
      "titulo": "INFORMAÇÕES BÁSICAS",
      "linhas": [
        "Nome e Tradução: Muktāsāra (मुक्तासार) - \"Essência de Liberação\" ou \"Essência do Infinito\"",
        "Tipo: Ourives / Professor Espiritual",
        "Localização: Cidade de Bharukaccha, região sul",
        "Status: Ativo como mestre bodhisattva em liberação mental"
      ],
      "conteudo": "Nome e Tradução: Muktāsāra (मुक्तासार) - \"Essência de Liberação\" ou \"Essência do Infinito\"\nTipo: Ourives / Professor Espiritual\nLocalização: Cidade de Bharukaccha, região sul\nStatus: Ativo como mestre bodhisattva em liberação mental"
    },
    {
      "titulo": "DESCRIÇÃO FÍSICA",
      "linhas": [
        "Aparência Visual",
        "",
        "Cor do Corpo: Não especificada no texto",
        "Cabelo: Não especificado no texto",
        "Olhos: Não especificado no texto",
        "Beleza Geral: Não especificada, mas comunicativa de sabedoria e serenidade",
        "Adornos: Provavelmente adornos associados à sua profissão de ourives",
        "Vestimentas: Não especificadas, mas apropriadas para um artesão culto"
      ],
      "conteudo": "Aparência Visual\n\nCor do Corpo: Não especificada no texto\nCabelo: Não especificado no texto\nOlhos: Não especificado no texto\nBeleza Geral: Não especificada, mas comunicativa de sabedoria e serenidade\nAdornos: Provavelmente adornos associados à sua profissão de ourives\nVestimentas: Não especificadas, mas apropriadas para um artesão culto"
    },
    {
      "titulo": "CARACTERÍSTICAS ESPIRITUAIS DISTINTIVAS",
      "linhas": [
        "- Mestre de Liberação Bodhisattva \"Exibição de Memória Pura Sem Impedimentos\"",
        "- Buscador contínuo do Dharma aos pés de todos os tathāgatas",
        "- Especializado em memórias conectando muitos budas (tathāgatas)",
        "- Conhecedor da continuidade e pureza da memória espiritual",
        "- Humilde em reconhecer suas próprias limitações e deferência aos grandes mestres"
      ],
      "conteudo": "- Mestre de Liberação Bodhisattva \"Exibição de Memória Pura Sem Impedimentos\"\n- Buscador contínuo do Dharma aos pés de todos os tathāgatas\n- Especializado em memórias conectando muitos budas (tathāgatas)\n- Conhecedor da continuidade e pureza da memória espiritual\n- Humilde em reconhecer suas próprias limitações e deferência aos grandes mestres"
    },
    {
      "titulo": "EXPERIÊNCIA MÍSTICA CENTRAL",
      "linhas": [
        "Muktāsāra alcançou a liberação espiritual através da \"Exibição de Memória Pura Sem Impedimentos\". ",
        "Isso lhe permite participar constantemente de ensinamentos nos dez cantos do universo, ",
        "apresentando sabedoria fluida e continua entre muitos budas."
      ],
      "conteudo": "Muktāsāra alcançou a liberação espiritual através da \"Exibição de Memória Pura Sem Impedimentos\". \nIsso lhe permite participar constantemente de ensinamentos nos dez cantos do universo, \napresentando sabedoria fluida e continua entre muitos budas."
    },
    {
      "titulo": "A principal experiência mística é o acesso e a manutenção de memoria infalível relacionada",
      "linhas": [
        "aos ensinamentos dos tathāgatas, transcendendo tempo e espaço convencional."
      ],
      "conteudo": "aos ensinamentos dos tathāgatas, transcendendo tempo e espaço convencional."
    },
    {
      "titulo": "LOCALIZAÇÃO E CONTEXTO",
      "linhas": [
        "Residente da cidade de Bharukaccha na região sul, Muktāsāra representa o arquétipo do ",
        "ourives iluminado. Ele une suas habilidades artesanais com profundidade espiritual, ",
        "demonstrando que profissão e aperfeiçoamento espiritual podem andar juntos."
      ],
      "conteudo": "Residente da cidade de Bharukaccha na região sul, Muktāsāra representa o arquétipo do \nourives iluminado. Ele une suas habilidades artesanais com profundidade espiritual, \ndemonstrando que profissão e aperfeiçoamento espiritual podem andar juntos."
    },
    {
      "titulo": "ANÁLISE ESPECIAL",
      "linhas": [
        "Este capítulo introduz um mestre que incorpora o equilíbrio entre habilidade mundana ",
        "e sabedoria espiritual. Muktāsāra exemplifica como o talento profissional pode ser ",
        "integrado à prática Bodhisattva para criar uma vida de verdadeira realização.",
        "",
        "Seus ensinamentos refletem a importância do \"leão intrépido\", aqueles bodhisattvas que ",
        "garantem grande mérito e sabedoria além do que é óbvio para o mundo secular."
      ],
      "conteudo": "Este capítulo introduz um mestre que incorpora o equilíbrio entre habilidade mundana \ne sabedoria espiritual. Muktāsāra exemplifica como o talento profissional pode ser \nintegrado à prática Bodhisattva para criar uma vida de verdadeira realização.\n\nSeus ensinamentos refletem a importância do \"leão intrépido\", aqueles bodhisattvas que \ngarantem grande mérito e sabedoria além do que é óbvio para o mundo secular."
    },
    {
      "titulo": "{DESCRIÇÃO GENERATIVA:",
      "linhas": [
        "Create a venerable and wise goldsmith named Muktāsāra, representing \"Essence of Liberation\". ",
        "He should appear as an enlightened artisan, with a calm and serene demeanor conveying ",
        "both craft mastery and spiritual depth. Include elements suggesting his profession, such as ",
        "wearing tools or surrounded by jewels, with clothing suitable for a skilled and learned artisan. ",
        "His presence should exude a sense of infinite wisdom and timeless memory, with an expression ",
        "that reflects continuous learning and deep reflection. Blank background.}"
      ],
      "conteudo": "Create a venerable and wise goldsmith named Muktāsāra, representing \"Essence of Liberation\". \nHe should appear as an enlightened artisan, with a calm and serene demeanor conveying \nboth craft mastery and spiritual depth. Include elements suggesting his profession, such as \nwearing tools or surrounded by jewels, with clothing suitable for a skilled and learned artisan. \nHis presence should exude a sense of infinite wisdom and timeless memory, with an expression \nthat reflects continuous learning and deep reflection. Blank background.}"
    }
  ]
}