{
  "titulo_principal": "Título não identificado",
  "conteudo_completo": "NOME DO PERSONAGEM\n\nSāgara megha\n\nINFORMAÇÕES BÁSICAS\n\nNome e Tradução: Sāgara megha (Nuvem do Oceano)\nTipo: Bhikṣu (Monge budista)\nLocalização: Área chamada Sāgara mukha (Boca do Oceano)\nStatus: Mestre do ensinamento do Dharma \"Olhos que Veem Tudo\", contemplador do oceano\n\nDESCRIÇÃO FÍSICA\nAparência Visual\n\nCor do Corpo: Não especificado diretamente\nCabelo: Não especificado\nOlhos: Não especificado fisicamente\nBeleza Geral: Não descrita em detalhes físicos\nAdornos: Não especificado\nVestimentas: Vestes de bhikṣu (monge budista)\n\nCARACTERÍSTICAS ESPIRITUAIS DISTINTIVAS\n\n- Mestre do ensinamento \"All-Seeing Eyes\" (Olhos que Veem Tudo)\n- Contemplou o grande oceano por 12 anos\n- Teve visão de um Tathāgata emergindo de um grande lótus no oceano\n- Possui múltiplos poderes de retenção (dhāraṇī)\n- Capaz de ensinar seres de todas as direções\n- Domina o ensinamento que revela a conduta dos bodhisattvas\n- Possui sabedoria para comunicar com todos os tipos de seres\n\nEXPERIÊNCIA MÍSTICA CENTRAL\n\n- Presenciou o surgimento de um grande lótus do oceano\n- Viu um Tathāgata sentado no lótus, estendendo-se até o topo da existência\n- Recebeu o toque da mão direita do Tathāgata em sua cabeça\n- Foi ensinado diretamente pelo Tathāgata o Dharma \"All-Seeing Eyes\"\n- Testemunhou seres celestiais prestando homenagem ao lótus\n\nLOCALIZAÇÃO E CONTEXTO\n\n- Reside há 12 anos contemplando o grande oceano\n- Localizado na área Sāgara mukha\n- Ensina seres de todas as dez direções\n- Permanece voltado para o oceano em contemplação contínua\n\n\n",
  "dados_estruturados": {
    "informacoes_basicas": {
      "nome_e_traducao": "Sāgara megha (Nuvem do Oceano)",
      "tipo": "Bhikṣu (Monge budista)",
      "localizacao": "Área chamada Sāgara mukha (Boca do Oceano)",
      "status": "Mestre do ensinamento do Dharma \"Olhos que Veem Tudo\", contemplador do oceano"
    },
    "descricao_fisica": {
      "cor_do_corpo": "Não especificado diretamente",
      "cabelo": "Não especificado",
      "olhos": "Não especificado fisicamente",
      "beleza_geral": "Não descrita em detalhes físicos",
      "adornos": "Não especificado",
      "vestimentas": "Vestes de bhikṣu (monge budista)"
    },
    "caracteristicas_espirituais": [
      "- Mestre do ensinamento \"All-Seeing Eyes\" (Olhos que Veem Tudo)",
      "- Contemplou o grande oceano por 12 anos",
      "- Teve visão de um Tathāgata emergindo de um grande lótus no oceano",
      "- Possui múltiplos poderes de retenção (dhāraṇī)",
      "- Capaz de ensinar seres de todas as direções",
      "- Domina o ensinamento que revela a conduta dos bodhisattvas",
      "- Possui sabedoria para comunicar com todos os tipos de seres"
    ],
    "experiencia_mistica": "- Presenciou o surgimento de um grande lótus do oceano\n- Viu um Tathāgata sentado no lótus, estendendo-se até o topo da existência\n- Recebeu o toque da mão direita do Tathāgata em sua cabeça\n- Foi ensinado diretamente pelo Tathāgata o Dharma \"All-Seeing Eyes\"\n- Testemunhou seres celestiais prestando homenagem ao lótus",
    "localizacao_contexto": "- Reside há 12 anos contemplando o grande oceano\n- Localizado na área Sāgara mukha\n- Ensina seres de todas as dez direções\n- Permanece voltado para o oceano em contemplação contínua"
  },
  "secoes_organizadas": [
    {
      "titulo": "NOME DO PERSONAGEM",
      "linhas": [
        "Sāgara megha"
      ],
      "conteudo": "Sāgara megha"
    },
    {
      "titulo": "INFORMAÇÕES BÁSICAS",
      "linhas": [
        "Nome e Tradução: Sāgara megha (Nuvem do Oceano)",
        "Tipo: Bhikṣu (Monge budista)",
        "Localização: Área chamada Sāgara mukha (Boca do Oceano)",
        "Status: Mestre do ensinamento do Dharma \"Olhos que Veem Tudo\", contemplador do oceano"
      ],
      "conteudo": "Nome e Tradução: Sāgara megha (Nuvem do Oceano)\nTipo: Bhikṣu (Monge budista)\nLocalização: Área chamada Sāgara mukha (Boca do Oceano)\nStatus: Mestre do ensinamento do Dharma \"Olhos que Veem Tudo\", contemplador do oceano"
    },
    {
      "titulo": "DESCRIÇÃO FÍSICA",
      "linhas": [
        "Aparência Visual",
        "",
        "Cor do Corpo: Não especificado diretamente",
        "Cabelo: Não especificado",
        "Olhos: Não especificado fisicamente",
        "Beleza Geral: Não descrita em detalhes físicos",
        "Adornos: Não especificado",
        "Vestimentas: Vestes de bhikṣu (monge budista)"
      ],
      "conteudo": "Aparência Visual\n\nCor do Corpo: Não especificado diretamente\nCabelo: Não especificado\nOlhos: Não especificado fisicamente\nBeleza Geral: Não descrita em detalhes físicos\nAdornos: Não especificado\nVestimentas: Vestes de bhikṣu (monge budista)"
    },
    {
      "titulo": "CARACTERÍSTICAS ESPIRITUAIS DISTINTIVAS",
      "linhas": [
        "- Mestre do ensinamento \"All-Seeing Eyes\" (Olhos que Veem Tudo)",
        "- Contemplou o grande oceano por 12 anos",
        "- Teve visão de um Tathāgata emergindo de um grande lótus no oceano",
        "- Possui múltiplos poderes de retenção (dhāraṇī)",
        "- Capaz de ensinar seres de todas as direções",
        "- Domina o ensinamento que revela a conduta dos bodhisattvas",
        "- Possui sabedoria para comunicar com todos os tipos de seres"
      ],
      "conteudo": "- Mestre do ensinamento \"All-Seeing Eyes\" (Olhos que Veem Tudo)\n- Contemplou o grande oceano por 12 anos\n- Teve visão de um Tathāgata emergindo de um grande lótus no oceano\n- Possui múltiplos poderes de retenção (dhāraṇī)\n- Capaz de ensinar seres de todas as direções\n- Domina o ensinamento que revela a conduta dos bodhisattvas\n- Possui sabedoria para comunicar com todos os tipos de seres"
    },
    {
      "titulo": "EXPERIÊNCIA MÍSTICA CENTRAL",
      "linhas": [
        "- Presenciou o surgimento de um grande lótus do oceano",
        "- Viu um Tathāgata sentado no lótus, estendendo-se até o topo da existência",
        "- Recebeu o toque da mão direita do Tathāgata em sua cabeça",
        "- Foi ensinado diretamente pelo Tathāgata o Dharma \"All-Seeing Eyes\"",
        "- Testemunhou seres celestiais prestando homenagem ao lótus"
      ],
      "conteudo": "- Presenciou o surgimento de um grande lótus do oceano\n- Viu um Tathāgata sentado no lótus, estendendo-se até o topo da existência\n- Recebeu o toque da mão direita do Tathāgata em sua cabeça\n- Foi ensinado diretamente pelo Tathāgata o Dharma \"All-Seeing Eyes\"\n- Testemunhou seres celestiais prestando homenagem ao lótus"
    },
    {
      "titulo": "LOCALIZAÇÃO E CONTEXTO",
      "linhas": [
        "- Reside há 12 anos contemplando o grande oceano",
        "- Localizado na área Sāgara mukha",
        "- Ensina seres de todas as dez direções",
        "- Permanece voltado para o oceano em contemplação contínua"
      ],
      "conteudo": "- Reside há 12 anos contemplando o grande oceano\n- Localizado na área Sāgara mukha\n- Ensina seres de todas as dez direções\n- Permanece voltado para o oceano em contemplação contínua"
    }
  ],
  "metadados": {
    "total_linhas": 48,
    "total_caracteres": 1525,
    "secoes_encontradas": 6,
    "dados_estruturados_extraidos": 5
  },
  "arquivo_origem": "Sagara_megha_Perfil.txt",
  "caminho_completo": "C:\\Users\\rouxy\\TECHNOSUTRA1\\technosutra\\characters\\Sagara_megha_Perfil.txt"
}