{
  "titulo_principal": "Título não identificado",
  "conteudo_completo": "NOME DO PERSONAGEM\n\nSupratiṣṭhita\n\nINFORMAÇÕES BÁSICAS\n\nNome e Tradução: Supratiṣṭhita (Bem Estabelecido)\nTipo: Bhikṣu (Monge budista)\nLocalização: Sāgara tīra na região de Laṅka\nStatus: Mestre da liberação bodhisattva do \"portal desobstruído\", praticante de poderes miraculosos\n\nDESCRIÇÃO FÍSICA\nAparência Visual\n\nCor do Corpo: Não especificado diretamente\nCabelo: Não especificado\nOlhos: Não especificado fisicamente\nBeleza Geral: Não descrita em detalhes físicos\nAdornos: Não especificado\nVestimentas: Vestes de bhikṣu (monge budista)\n\nCARACTERÍSTICAS ESPIRITUAIS DISTINTIVAS\n\n- Mestre da \"liberação bodhisattva do portal desobstruído\"\n- Possui poderes miraculosos não-compostos\n- Capaz de caminhar no céu sem impedimentos\n- Presença incorpórea que pervade reinos búdicos\n- Conhecimento desobstruído das mentes de todos os seres\n- Memória de vidas passadas sem impedimentos\n- Capacidade de transformação física múltipla\n- Domínio sobre elementos (fogo, fumaça, água, terra)\n\nPODERES MIRACULOSOS ESPECÍFICOS\n\n- Caminha, fica de pé, senta e se deita no céu\n- Torna-se invisível e reaparece\n- Transforma-se em fumaça e fogo\n- Multiplica-se (um em muitos, muitos em um)\n- Passa através de paredes e muralhas como no espaço\n- Voa através do ar sentado em posição de lótus\n- Mergulha na terra como um pássaro na água\n- Caminha sobre a água sem afundar\n- Produz fumaça e chamas como um grande fogo\n- Faz a terra tremer\n- Toca o sol e a lua com as mãos\n- Domina fisicamente até o mundo de Brahmā\n\nSÉQUITO CELESTIAL\n\n- Acompanhado por incontáveis centenas de milhares de devas\n- Recebe oferendas de senhores devas com pétalas divinas\n- Nāga senhores criam nuvens de incenso perfumado\n- Kinnara senhores oferecem canções de louvor\n- Mahoraga senhores trazem nuvens de roupas finas\n- Asura senhores conjuram nuvens de joias preciosas\n- Garuḍa senhores em forma humana fazem homenagem\n- Yakṣa senhores com corpos feios mas amor devotado\n- Rākṣasa senhores circulam protegendo-o\n- Brahmakāyika senhores cantam louvores\n- Śuddhāvāsa devas fazem oferendas de seus palácios aéreos\n\nLOCALIZAÇÃO E CONTEXTO\n\n- Encontrado caminhando no céu\n- Localizado em Sāgara tīra, região de Laṅka\n- Constantemente rodeado por seres celestiais em homenagem\n- Capaz de viajar instantaneamente através de incontáveis reinos mundiais\n",
  "dados_estruturados": {
    "informacoes_basicas": {
      "nome_e_traducao": "Supratiṣṭhita (Bem Estabelecido)",
      "tipo": "Bhikṣu (Monge budista)",
      "localizacao": "Sāgara tīra na região de Laṅka",
      "status": "Mestre da liberação bodhisattva do \"portal desobstruído\", praticante de poderes miraculosos"
    },
    "descricao_fisica": {
      "cor_do_corpo": "Não especificado diretamente",
      "cabelo": "Não especificado",
      "olhos": "Não especificado fisicamente",
      "beleza_geral": "Não descrita em detalhes físicos",
      "adornos": "Não especificado",
      "vestimentas": "Vestes de bhikṣu (monge budista)"
    },
    "caracteristicas_espirituais": [
      "- Mestre da \"liberação bodhisattva do portal desobstruído\"",
      "- Possui poderes miraculosos não-compostos",
      "- Capaz de caminhar no céu sem impedimentos",
      "- Presença incorpórea que pervade reinos búdicos",
      "- Conhecimento desobstruído das mentes de todos os seres",
      "- Memória de vidas passadas sem impedimentos",
      "- Capacidade de transformação física múltipla",
      "- Domínio sobre elementos (fogo, fumaça, água, terra)",
      "",
      "PODERES MIRACULOSOS ESPECÍFICOS",
      "",
      "- Caminha, fica de pé, senta e se deita no céu",
      "- Torna-se invisível e reaparece",
      "- Transforma-se em fumaça e fogo",
      "- Multiplica-se (um em muitos, muitos em um)",
      "- Passa através de paredes e muralhas como no espaço",
      "- Voa através do ar sentado em posição de lótus",
      "- Mergulha na terra como um pássaro na água",
      "- Caminha sobre a água sem afundar",
      "- Produz fumaça e chamas como um grande fogo",
      "- Faz a terra tremer",
      "- Toca o sol e a lua com as mãos",
      "- Domina fisicamente até o mundo de Brahmā",
      "",
      "SÉQUITO CELESTIAL",
      "",
      "- Acompanhado por incontáveis centenas de milhares de devas",
      "- Recebe oferendas de senhores devas com pétalas divinas",
      "- Nāga senhores criam nuvens de incenso perfumado",
      "- Kinnara senhores oferecem canções de louvor",
      "- Mahoraga senhores trazem nuvens de roupas finas",
      "- Asura senhores conjuram nuvens de joias preciosas",
      "- Garuḍa senhores em forma humana fazem homenagem",
      "- Yakṣa senhores com corpos feios mas amor devotado",
      "- Rākṣasa senhores circulam protegendo-o",
      "- Brahmakāyika senhores cantam louvores",
      "- Śuddhāvāsa devas fazem oferendas de seus palácios aéreos"
    ],
    "localizacao_contexto": "- Encontrado caminhando no céu\n- Localizado em Sāgara tīra, região de Laṅka\n- Constantemente rodeado por seres celestiais em homenagem\n- Capaz de viajar instantaneamente através de incontáveis reinos mundiais"
  },
  "secoes_organizadas": [
    {
      "titulo": "NOME DO PERSONAGEM",
      "linhas": [
        "Supratiṣṭhita"
      ],
      "conteudo": "Supratiṣṭhita"
    },
    {
      "titulo": "INFORMAÇÕES BÁSICAS",
      "linhas": [
        "Nome e Tradução: Supratiṣṭhita (Bem Estabelecido)",
        "Tipo: Bhikṣu (Monge budista)",
        "Localização: Sāgara tīra na região de Laṅka",
        "Status: Mestre da liberação bodhisattva do \"portal desobstruído\", praticante de poderes miraculosos"
      ],
      "conteudo": "Nome e Tradução: Supratiṣṭhita (Bem Estabelecido)\nTipo: Bhikṣu (Monge budista)\nLocalização: Sāgara tīra na região de Laṅka\nStatus: Mestre da liberação bodhisattva do \"portal desobstruído\", praticante de poderes miraculosos"
    },
    {
      "titulo": "DESCRIÇÃO FÍSICA",
      "linhas": [
        "Aparência Visual",
        "",
        "Cor do Corpo: Não especificado diretamente",
        "Cabelo: Não especificado",
        "Olhos: Não especificado fisicamente",
        "Beleza Geral: Não descrita em detalhes físicos",
        "Adornos: Não especificado",
        "Vestimentas: Vestes de bhikṣu (monge budista)"
      ],
      "conteudo": "Aparência Visual\n\nCor do Corpo: Não especificado diretamente\nCabelo: Não especificado\nOlhos: Não especificado fisicamente\nBeleza Geral: Não descrita em detalhes físicos\nAdornos: Não especificado\nVestimentas: Vestes de bhikṣu (monge budista)"
    },
    {
      "titulo": "CARACTERÍSTICAS ESPIRITUAIS DISTINTIVAS",
      "linhas": [
        "- Mestre da \"liberação bodhisattva do portal desobstruído\"",
        "- Possui poderes miraculosos não-compostos",
        "- Capaz de caminhar no céu sem impedimentos",
        "- Presença incorpórea que pervade reinos búdicos",
        "- Conhecimento desobstruído das mentes de todos os seres",
        "- Memória de vidas passadas sem impedimentos",
        "- Capacidade de transformação física múltipla",
        "- Domínio sobre elementos (fogo, fumaça, água, terra)",
        "",
        "PODERES MIRACULOSOS ESPECÍFICOS",
        "",
        "- Caminha, fica de pé, senta e se deita no céu",
        "- Torna-se invisível e reaparece",
        "- Transforma-se em fumaça e fogo",
        "- Multiplica-se (um em muitos, muitos em um)",
        "- Passa através de paredes e muralhas como no espaço",
        "- Voa através do ar sentado em posição de lótus",
        "- Mergulha na terra como um pássaro na água",
        "- Caminha sobre a água sem afundar",
        "- Produz fumaça e chamas como um grande fogo",
        "- Faz a terra tremer",
        "- Toca o sol e a lua com as mãos",
        "- Domina fisicamente até o mundo de Brahmā",
        "",
        "SÉQUITO CELESTIAL",
        "",
        "- Acompanhado por incontáveis centenas de milhares de devas",
        "- Recebe oferendas de senhores devas com pétalas divinas",
        "- Nāga senhores criam nuvens de incenso perfumado",
        "- Kinnara senhores oferecem canções de louvor",
        "- Mahoraga senhores trazem nuvens de roupas finas",
        "- Asura senhores conjuram nuvens de joias preciosas",
        "- Garuḍa senhores em forma humana fazem homenagem",
        "- Yakṣa senhores com corpos feios mas amor devotado",
        "- Rākṣasa senhores circulam protegendo-o",
        "- Brahmakāyika senhores cantam louvores",
        "- Śuddhāvāsa devas fazem oferendas de seus palácios aéreos"
      ],
      "conteudo": "- Mestre da \"liberação bodhisattva do portal desobstruído\"\n- Possui poderes miraculosos não-compostos\n- Capaz de caminhar no céu sem impedimentos\n- Presença incorpórea que pervade reinos búdicos\n- Conhecimento desobstruído das mentes de todos os seres\n- Memória de vidas passadas sem impedimentos\n- Capacidade de transformação física múltipla\n- Domínio sobre elementos (fogo, fumaça, água, terra)\n\nPODERES MIRACULOSOS ESPECÍFICOS\n\n- Caminha, fica de pé, senta e se deita no céu\n- Torna-se invisível e reaparece\n- Transforma-se em fumaça e fogo\n- Multiplica-se (um em muitos, muitos em um)\n- Passa através de paredes e muralhas como no espaço\n- Voa através do ar sentado em posição de lótus\n- Mergulha na terra como um pássaro na água\n- Caminha sobre a água sem afundar\n- Produz fumaça e chamas como um grande fogo\n- Faz a terra tremer\n- Toca o sol e a lua com as mãos\n- Domina fisicamente até o mundo de Brahmā\n\nSÉQUITO CELESTIAL\n\n- Acompanhado por incontáveis centenas de milhares de devas\n- Recebe oferendas de senhores devas com pétalas divinas\n- Nāga senhores criam nuvens de incenso perfumado\n- Kinnara senhores oferecem canções de louvor\n- Mahoraga senhores trazem nuvens de roupas finas\n- Asura senhores conjuram nuvens de joias preciosas\n- Garuḍa senhores em forma humana fazem homenagem\n- Yakṣa senhores com corpos feios mas amor devotado\n- Rākṣasa senhores circulam protegendo-o\n- Brahmakāyika senhores cantam louvores\n- Śuddhāvāsa devas fazem oferendas de seus palácios aéreos"
    },
    {
      "titulo": "LOCALIZAÇÃO E CONTEXTO",
      "linhas": [
        "- Encontrado caminhando no céu",
        "- Localizado em Sāgara tīra, região de Laṅka",
        "- Constantemente rodeado por seres celestiais em homenagem",
        "- Capaz de viajar instantaneamente através de incontáveis reinos mundiais"
      ],
      "conteudo": "- Encontrado caminhando no céu\n- Localizado em Sāgara tīra, região de Laṅka\n- Constantemente rodeado por seres celestiais em homenagem\n- Capaz de viajar instantaneamente através de incontáveis reinos mundiais"
    }
  ],
  "metadados": {
    "total_linhas": 68,
    "total_caracteres": 2302,
    "secoes_encontradas": 5,
    "dados_estruturados_extraidos": 4
  },
  "arquivo_origem": "Supratisthita_Perfil.txt",
  "caminho_completo": "C:\\Users\\rouxy\\TECHNOSUTRA1\\technosutra\\characters\\Supratisthita_Perfil.txt"
}