{
  "titulo_principal": "PERFIL DE PERSONAGEM - CAPÍTULO 34",
  "conteudo_completo": "═══════════════════════════════════════════════════════════════════════════════\n                            PERFIL DE PERSONAGEM - CAPÍTULO 34\n═══════════════════════════════════════════════════════════════════════════════\n\nNOME DO PERSONAGEM: VĀSANTĪ (वासंती)\n\nINFORMAÇÕES BÁSICAS\n═══════════════════════════════════════════════════════════════════════════════\n\nNome e Tradução: Vāsantī - Associada com o \"Vidya\" ou \"Primavera\"\nTipo: Deusa da Noite, Professora Espiritual / Kalyāṇamitra\nLocalização: Além dos céus sobre Kapilavastu\nStatus: Deidade celestial de sabedoria e iluminação\n\nDESCRIÇÃO FÍSICA\n═══════════════════════════════════════════════════════════════════════════════\n\nAparência Visual\n───────────────────────────────────────────────────────────────────────────────\n• Corpo da cor do ouro, visualmente encantador e belo\n• Cabelos e olhos de um preto profundo, suave e abundante\n• Adornada em joias preciosas com ornamentos sagrados\n• Vestida em vestimentas tingidas e um tipo de penteado adornado com o disco lunar\n• Constelações, planetas e estrelas visíveis dentro de seu corpo\n\nCARACTERÍSTICAS ESPIRITUAIS DISTINTIVAS\n═══════════════════════════════════════════════════════════════════════════════\n\n• Mestre da \"Liberação Bodhisattva chamada 'O Portal para Guiar os Seres através da\n  Irradiação do Dharma que Elimina a Escuridão de Todos os Seres'\"\n• Capaz de manifestar corpos e fenômenos diversos para guiar seres em samsara\n• Protege seres em perigo ou perdidos, guiando-os para segurança\n• Sabedoria capaz de dispensar escuridão e ignorância\n\nEXPERIÊNCIA MÍSTICA CENTRAL\n═══════════════════════════════════════════════════════════════════════════════\n\nEm sua história cósmica:\n• Era uma rainha que foi inspirada pela iluminação do Tathāgata\n• Obteve sua liberação sob este Tathāgata através de grande mérito acumulado\n• Pervade mundos incontáveis em um instante mental, abençoando e guiando todos os seres\n\nLOCALIZAÇÃO E CONTEXTO\n═══════════════════════════════════════════════════════════════════════════════\n\nOrigem: Kapilavastu e domínio celestial\nLocalização Atual: Plana no céu sobre Kapilavastu\nEncontro: Sudhana é guiado a ela pela sabedoria de kalyāṇamitras anteriores\n\nSABEDORIA DISTINTIVA\n═══════════════════════════════════════════════════════════════════════════════\n\nVāsantī simboliza a iluminação e a sabedoria que atravessam a escuridão. Ela guia seres perdidos através \nde métodos diversos e compassivos. Sua presença traz o potencial de iluminação para aqueles que a veem \nou ouvem seu nome.\n\nSÍNTESE DESCRITIVA\n═══════════════════════════════════════════════════════════════════════════════\n\n\"Vāsantī, celestial night goddess, seated above Kapilavastu in a jewel-encrusted palace, \nsurrounded by stars and celestial phenomena. Her golden skin glows softly, hair and eyes \ndeep black, adorned with jewels and a lunar crown. She emanates a peaceful and wise \npresence, clothed in richly dyed fabrics with cosmic symbols. She embodies the balance of \nnight's mystery and illuminating wisdom, radiating guidance to all directions. Blank background.\"\n\n═══════════════════════════════════════════════════════════════════════════════\n                                  FIM DO PERFIL\n═══════════════════════════════════════════════════════════════════════════════\n",
  "dados_estruturados": {
    "informacoes_basicas": {
      "nome_e_traducao": "Vāsantī - Associada com o \"Vidya\" ou \"Primavera\"",
      "tipo": "Deusa da Noite, Professora Espiritual / Kalyāṇamitra",
      "localizacao": "Além dos céus sobre Kapilavastu",
      "status": "Deidade celestial de sabedoria e iluminação"
    },
    "descricao_fisica": {},
    "caracteristicas_espirituais": [
      "═══════════════════════════════════════════════════════════════════════════════",
      "",
      "• Mestre da \"Liberação Bodhisattva chamada 'O Portal para Guiar os Seres através da",
      "  Irradiação do Dharma que Elimina a Escuridão de Todos os Seres'\"",
      "• Capaz de manifestar corpos e fenômenos diversos para guiar seres em samsara",
      "• Protege seres em perigo ou perdidos, guiando-os para segurança",
      "• Sabedoria capaz de dispensar escuridão e ignorância"
    ],
    "experiencia_mistica": "═══════════════════════════════════════════════════════════════════════════════\n\nEm sua história cósmica:\n• Era uma rainha que foi inspirada pela iluminação do Tathāgata\n• Obteve sua liberação sob este Tathāgata através de grande mérito acumulado\n• Pervade mundos incontáveis em um instante mental, abençoando e guiando todos os seres",
    "localizacao_contexto": "═══════════════════════════════════════════════════════════════════════════════\n\nOrigem: Kapilavastu e domínio celestial\nLocalização Atual: Plana no céu sobre Kapilavastu\nEncontro: Sudhana é guiado a ela pela sabedoria de kalyāṇamitras anteriores\n\nSABEDORIA DISTINTIVA\n═══════════════════════════════════════════════════════════════════════════════\n\nVāsantī simboliza a iluminação e a sabedoria que atravessam a escuridão. Ela guia seres perdidos através \nde métodos diversos e compassivos. Sua presença traz o potencial de iluminação para aqueles que a veem \nou ouvem seu nome."
  },
  "secoes_organizadas": [
    {
      "titulo": "INFORMAÇÕES BÁSICAS",
      "linhas": [
        "═══════════════════════════════════════════════════════════════════════════════",
        "",
        "Nome e Tradução: Vāsantī - Associada com o \"Vidya\" ou \"Primavera\"",
        "Tipo: Deusa da Noite, Professora Espiritual / Kalyāṇamitra",
        "Localização: Além dos céus sobre Kapilavastu",
        "Status: Deidade celestial de sabedoria e iluminação"
      ],
      "conteudo": "═══════════════════════════════════════════════════════════════════════════════\n\nNome e Tradução: Vāsantī - Associada com o \"Vidya\" ou \"Primavera\"\nTipo: Deusa da Noite, Professora Espiritual / Kalyāṇamitra\nLocalização: Além dos céus sobre Kapilavastu\nStatus: Deidade celestial de sabedoria e iluminação"
    },
    {
      "titulo": "DESCRIÇÃO FÍSICA",
      "linhas": [
        "═══════════════════════════════════════════════════════════════════════════════",
        "",
        "Aparência Visual",
        "───────────────────────────────────────────────────────────────────────────────",
        "• Corpo da cor do ouro, visualmente encantador e belo",
        "• Cabelos e olhos de um preto profundo, suave e abundante",
        "• Adornada em joias preciosas com ornamentos sagrados",
        "• Vestida em vestimentas tingidas e um tipo de penteado adornado com o disco lunar",
        "• Constelações, planetas e estrelas visíveis dentro de seu corpo"
      ],
      "conteudo": "═══════════════════════════════════════════════════════════════════════════════\n\nAparência Visual\n───────────────────────────────────────────────────────────────────────────────\n• Corpo da cor do ouro, visualmente encantador e belo\n• Cabelos e olhos de um preto profundo, suave e abundante\n• Adornada em joias preciosas com ornamentos sagrados\n• Vestida em vestimentas tingidas e um tipo de penteado adornado com o disco lunar\n• Constelações, planetas e estrelas visíveis dentro de seu corpo"
    },
    {
      "titulo": "CARACTERÍSTICAS ESPIRITUAIS DISTINTIVAS",
      "linhas": [
        "═══════════════════════════════════════════════════════════════════════════════",
        "",
        "• Mestre da \"Liberação Bodhisattva chamada 'O Portal para Guiar os Seres através da",
        "  Irradiação do Dharma que Elimina a Escuridão de Todos os Seres'\"",
        "• Capaz de manifestar corpos e fenômenos diversos para guiar seres em samsara",
        "• Protege seres em perigo ou perdidos, guiando-os para segurança",
        "• Sabedoria capaz de dispensar escuridão e ignorância"
      ],
      "conteudo": "═══════════════════════════════════════════════════════════════════════════════\n\n• Mestre da \"Liberação Bodhisattva chamada 'O Portal para Guiar os Seres através da\n  Irradiação do Dharma que Elimina a Escuridão de Todos os Seres'\"\n• Capaz de manifestar corpos e fenômenos diversos para guiar seres em samsara\n• Protege seres em perigo ou perdidos, guiando-os para segurança\n• Sabedoria capaz de dispensar escuridão e ignorância"
    },
    {
      "titulo": "EXPERIÊNCIA MÍSTICA CENTRAL",
      "linhas": [
        "═══════════════════════════════════════════════════════════════════════════════",
        "",
        "Em sua história cósmica:",
        "• Era uma rainha que foi inspirada pela iluminação do Tathāgata",
        "• Obteve sua liberação sob este Tathāgata através de grande mérito acumulado",
        "• Pervade mundos incontáveis em um instante mental, abençoando e guiando todos os seres"
      ],
      "conteudo": "═══════════════════════════════════════════════════════════════════════════════\n\nEm sua história cósmica:\n• Era uma rainha que foi inspirada pela iluminação do Tathāgata\n• Obteve sua liberação sob este Tathāgata através de grande mérito acumulado\n• Pervade mundos incontáveis em um instante mental, abençoando e guiando todos os seres"
    },
    {
      "titulo": "LOCALIZAÇÃO E CONTEXTO",
      "linhas": [
        "═══════════════════════════════════════════════════════════════════════════════",
        "",
        "Origem: Kapilavastu e domínio celestial",
        "Localização Atual: Plana no céu sobre Kapilavastu",
        "Encontro: Sudhana é guiado a ela pela sabedoria de kalyāṇamitras anteriores",
        "",
        "SABEDORIA DISTINTIVA",
        "═══════════════════════════════════════════════════════════════════════════════",
        "",
        "Vāsantī simboliza a iluminação e a sabedoria que atravessam a escuridão. Ela guia seres perdidos através ",
        "de métodos diversos e compassivos. Sua presença traz o potencial de iluminação para aqueles que a veem ",
        "ou ouvem seu nome."
      ],
      "conteudo": "═══════════════════════════════════════════════════════════════════════════════\n\nOrigem: Kapilavastu e domínio celestial\nLocalização Atual: Plana no céu sobre Kapilavastu\nEncontro: Sudhana é guiado a ela pela sabedoria de kalyāṇamitras anteriores\n\nSABEDORIA DISTINTIVA\n═══════════════════════════════════════════════════════════════════════════════\n\nVāsantī simboliza a iluminação e a sabedoria que atravessam a escuridão. Ela guia seres perdidos através \nde métodos diversos e compassivos. Sua presença traz o potencial de iluminação para aqueles que a veem \nou ouvem seu nome."
    },
    {
      "titulo": "SÍNTESE DESCRITIVA",
      "linhas": [
        "═══════════════════════════════════════════════════════════════════════════════",
        "",
        "\"Vāsantī, celestial night goddess, seated above Kapilavastu in a jewel-encrusted palace, ",
        "surrounded by stars and celestial phenomena. Her golden skin glows softly, hair and eyes ",
        "deep black, adorned with jewels and a lunar crown. She emanates a peaceful and wise ",
        "presence, clothed in richly dyed fabrics with cosmic symbols. She embodies the balance of ",
        "night's mystery and illuminating wisdom, radiating guidance to all directions. Blank background.\"",
        "",
        "═══════════════════════════════════════════════════════════════════════════════",
        "                                  FIM DO PERFIL",
        "═══════════════════════════════════════════════════════════════════════════════"
      ],
      "conteudo": "═══════════════════════════════════════════════════════════════════════════════\n\n\"Vāsantī, celestial night goddess, seated above Kapilavastu in a jewel-encrusted palace, \nsurrounded by stars and celestial phenomena. Her golden skin glows softly, hair and eyes \ndeep black, adorned with jewels and a lunar crown. She emanates a peaceful and wise \npresence, clothed in richly dyed fabrics with cosmic symbols. She embodies the balance of \nnight's mystery and illuminating wisdom, radiating guidance to all directions. Blank background.\"\n\n═══════════════════════════════════════════════════════════════════════════════\n                                  FIM DO PERFIL\n═══════════════════════════════════════════════════════════════════════════════"
    }
  ],
  "metadados": {
    "total_linhas": 69,
    "total_caracteres": 3296,
    "secoes_encontradas": 6,
    "dados_estruturados_extraidos": 5
  },
  "arquivo_origem": "Vasanti_Perfil.txt",
  "caminho_completo": "C:\\Users\\rouxy\\TECHNOSUTRA1\\technosutra\\characters\\Vasanti_Perfil.txt"
}