{
  "titulo_principal": "PERFIL DE PERSONAGEM - CAPÍTULO 46",
  "conteudo_completo": "═══════════════════════════════════════════════════════════════════════════════\n                            PERFIL DE PERSONAGEM - CAPÍTULO 46\n═══════════════════════════════════════════════════════════════════════════════\n\nVIŚVĀMITRA\n\nINFORMAÇÕES BÁSICAS\n\nNome e Tradução: Viśvāmitra (विश्वामित्र) - \"Amigo do Universo\" ou \"Amigo de Todos\"\nTipo: Professor/Mestre Espiritual - Especialista em Educação de Crianças\nLocalização: Cidade de Kapilavastu\nStatus: Ativo como professor e guia espiritual\n\nDESCRIÇÃO FÍSICA\nAparência Visual\n\nCor do Corpo: Não especificada no texto (características físicas não detalhadas)\nCabelo: Não especificado no texto\nOlhos: Não especificado no texto\nBeleza Geral: Não especificada, mas presumivelmente dignificada por sua posição\nAdornos: Não especificados no texto\nVestimentas: Não especificadas, mas provavelmente vestes apropriadas de um mestre\n\nCARACTERÍSTICAS ESPIRITUAIS DISTINTIVAS\n\n- Professor especializado no ensino de crianças (bālācārya)\n- Reconhecido como um Ārya (nobre/santo)\n- Receptor de reverências rituais (prostração, circum-ambulação)\n- Conhecedor dos ensinamentos bodhisattva\n- Humilde redirecionador - não retém estudantes por ego\n\nEXPERIÊNCIA MÍSTICA CENTRAL\n\nViśvāmitra representa o arquétipo do educador espiritual especializado na formação \nde jovens buscadores. Sua principal qualidade mística é a capacidade de reconhecer \nquando um estudante precisa de ensinamentos além de seu escopo, demonstrando \nsabedoria pedagógica ao direcionar Sudhana para Śilpābhijña, que possui \nconhecimento específico sobre \"a ciência das palavras dos bodhisattvas\".\n\nLOCALIZAÇÃO E CONTEXTO\n\nSituado em Kapilavastu, cidade histórica associada ao nascimento do Buddha, \nViśvāmitra atua como um elo na cadeia de professores que guiam Sudhana. \nSua breve aparição simboliza a importância da humildade docente e do \nreconhecimento dos próprios limites no ensino espiritual.\n\nANÁLISE ESPECIAL\n\nEste capítulo é notavelmente conciso, focando na virtude da humildade pedagógica. \nViśvāmitra não tenta impressionar ou reter o jovem buscador, mas imediatamente \no direciona para o próximo mestre apropriado. Isso demonstra que um verdadeiro \nprofessor espiritual não possui ego territorial sobre seus estudantes.\n\n{DESCRIÇÃO GENERATIVA: \nCreate a wise elderly Indian sage teacher named Viśvāmitra, specialized in teaching \nchildren. He should have a gentle, humble appearance with traditional Indian spiritual \nteacher characteristics - possibly graying hair, kind eyes, wearing simple traditional \nrobes suitable for a teacher in ancient Kapilavastu. His posture should convey \nhumility and wisdom, perhaps in a teaching gesture. Blank background.}\n",
  "dados_estruturados": {
    "informacoes_basicas": {
      "nome_e_traducao": "Viśvāmitra (विश्वामित्र) - \"Amigo do Universo\" ou \"Amigo de Todos\"",
      "tipo": "Professor/Mestre Espiritual - Especialista em Educação de Crianças",
      "localizacao": "Cidade de Kapilavastu",
      "status": "Ativo como professor e guia espiritual"
    },
    "descricao_fisica": {
      "cor_do_corpo": "Não especificada no texto (características físicas não detalhadas)",
      "cabelo": "Não especificado no texto",
      "olhos": "Não especificado no texto",
      "beleza_geral": "Não especificada, mas presumivelmente dignificada por sua posição",
      "adornos": "Não especificados no texto",
      "vestimentas": "Não especificadas, mas provavelmente vestes apropriadas de um mestre"
    },
    "caracteristicas_espirituais": [
      "- Professor especializado no ensino de crianças (bālācārya)",
      "- Reconhecido como um Ārya (nobre/santo)",
      "- Receptor de reverências rituais (prostração, circum-ambulação)",
      "- Conhecedor dos ensinamentos bodhisattva",
      "- Humilde redirecionador - não retém estudantes por ego"
    ],
    "experiencia_mistica": "Viśvāmitra representa o arquétipo do educador espiritual especializado na formação \nde jovens buscadores. Sua principal qualidade mística é a capacidade de reconhecer \nquando um estudante precisa de ensinamentos além de seu escopo, demonstrando \nsabedoria pedagógica ao direcionar Sudhana para Śilpābhijña, que possui \nconhecimento específico sobre \"a ciência das palavras dos bodhisattvas\".",
    "localizacao_contexto": "Situado em Kapilavastu, cidade histórica associada ao nascimento do Buddha, \nViśvāmitra atua como um elo na cadeia de professores que guiam Sudhana. \nSua breve aparição simboliza a importância da humildade docente e do \nreconhecimento dos próprios limites no ensino espiritual.",
    "analise_especial": "Este capítulo é notavelmente conciso, focando na virtude da humildade pedagógica. \nViśvāmitra não tenta impressionar ou reter o jovem buscador, mas imediatamente \no direciona para o próximo mestre apropriado. Isso demonstra que um verdadeiro \nprofessor espiritual não possui ego territorial sobre seus estudantes.",
    "prompt_ia": "Create a wise elderly Indian sage teacher named Viśvāmitra, specialized in teaching \nchildren. He should have a gentle, humble appearance with traditional Indian spiritual \nteacher characteristics - possibly graying hair, kind eyes, wearing simple traditional \nrobes suitable for a teacher in ancient Kapilavastu. His posture should convey \nhumility and wisdom, perhaps in a teaching gesture. Blank background."
  },
  "secoes_organizadas": [
    {
      "titulo": "INFORMAÇÕES BÁSICAS",
      "linhas": [
        "Nome e Tradução: Viśvāmitra (विश्वामित्र) - \"Amigo do Universo\" ou \"Amigo de Todos\"",
        "Tipo: Professor/Mestre Espiritual - Especialista em Educação de Crianças",
        "Localização: Cidade de Kapilavastu",
        "Status: Ativo como professor e guia espiritual"
      ],
      "conteudo": "Nome e Tradução: Viśvāmitra (विश्वामित्र) - \"Amigo do Universo\" ou \"Amigo de Todos\"\nTipo: Professor/Mestre Espiritual - Especialista em Educação de Crianças\nLocalização: Cidade de Kapilavastu\nStatus: Ativo como professor e guia espiritual"
    },
    {
      "titulo": "DESCRIÇÃO FÍSICA",
      "linhas": [
        "Aparência Visual",
        "",
        "Cor do Corpo: Não especificada no texto (características físicas não detalhadas)",
        "Cabelo: Não especificado no texto",
        "Olhos: Não especificado no texto",
        "Beleza Geral: Não especificada, mas presumivelmente dignificada por sua posição",
        "Adornos: Não especificados no texto",
        "Vestimentas: Não especificadas, mas provavelmente vestes apropriadas de um mestre"
      ],
      "conteudo": "Aparência Visual\n\nCor do Corpo: Não especificada no texto (características físicas não detalhadas)\nCabelo: Não especificado no texto\nOlhos: Não especificado no texto\nBeleza Geral: Não especificada, mas presumivelmente dignificada por sua posição\nAdornos: Não especificados no texto\nVestimentas: Não especificadas, mas provavelmente vestes apropriadas de um mestre"
    },
    {
      "titulo": "CARACTERÍSTICAS ESPIRITUAIS DISTINTIVAS",
      "linhas": [
        "- Professor especializado no ensino de crianças (bālācārya)",
        "- Reconhecido como um Ārya (nobre/santo)",
        "- Receptor de reverências rituais (prostração, circum-ambulação)",
        "- Conhecedor dos ensinamentos bodhisattva",
        "- Humilde redirecionador - não retém estudantes por ego"
      ],
      "conteudo": "- Professor especializado no ensino de crianças (bālācārya)\n- Reconhecido como um Ārya (nobre/santo)\n- Receptor de reverências rituais (prostração, circum-ambulação)\n- Conhecedor dos ensinamentos bodhisattva\n- Humilde redirecionador - não retém estudantes por ego"
    },
    {
      "titulo": "EXPERIÊNCIA MÍSTICA CENTRAL",
      "linhas": [
        "Viśvāmitra representa o arquétipo do educador espiritual especializado na formação ",
        "de jovens buscadores. Sua principal qualidade mística é a capacidade de reconhecer ",
        "quando um estudante precisa de ensinamentos além de seu escopo, demonstrando ",
        "sabedoria pedagógica ao direcionar Sudhana para Śilpābhijña, que possui ",
        "conhecimento específico sobre \"a ciência das palavras dos bodhisattvas\"."
      ],
      "conteudo": "Viśvāmitra representa o arquétipo do educador espiritual especializado na formação \nde jovens buscadores. Sua principal qualidade mística é a capacidade de reconhecer \nquando um estudante precisa de ensinamentos além de seu escopo, demonstrando \nsabedoria pedagógica ao direcionar Sudhana para Śilpābhijña, que possui \nconhecimento específico sobre \"a ciência das palavras dos bodhisattvas\"."
    },
    {
      "titulo": "LOCALIZAÇÃO E CONTEXTO",
      "linhas": [
        "Situado em Kapilavastu, cidade histórica associada ao nascimento do Buddha, ",
        "Viśvāmitra atua como um elo na cadeia de professores que guiam Sudhana. ",
        "Sua breve aparição simboliza a importância da humildade docente e do ",
        "reconhecimento dos próprios limites no ensino espiritual."
      ],
      "conteudo": "Situado em Kapilavastu, cidade histórica associada ao nascimento do Buddha, \nViśvāmitra atua como um elo na cadeia de professores que guiam Sudhana. \nSua breve aparição simboliza a importância da humildade docente e do \nreconhecimento dos próprios limites no ensino espiritual."
    },
    {
      "titulo": "ANÁLISE ESPECIAL",
      "linhas": [
        "Este capítulo é notavelmente conciso, focando na virtude da humildade pedagógica. ",
        "Viśvāmitra não tenta impressionar ou reter o jovem buscador, mas imediatamente ",
        "o direciona para o próximo mestre apropriado. Isso demonstra que um verdadeiro ",
        "professor espiritual não possui ego territorial sobre seus estudantes."
      ],
      "conteudo": "Este capítulo é notavelmente conciso, focando na virtude da humildade pedagógica. \nViśvāmitra não tenta impressionar ou reter o jovem buscador, mas imediatamente \no direciona para o próximo mestre apropriado. Isso demonstra que um verdadeiro \nprofessor espiritual não possui ego territorial sobre seus estudantes."
    },
    {
      "titulo": "{DESCRIÇÃO GENERATIVA:",
      "linhas": [
        "Create a wise elderly Indian sage teacher named Viśvāmitra, specialized in teaching ",
        "children. He should have a gentle, humble appearance with traditional Indian spiritual ",
        "teacher characteristics - possibly graying hair, kind eyes, wearing simple traditional ",
        "robes suitable for a teacher in ancient Kapilavastu. His posture should convey ",
        "humility and wisdom, perhaps in a teaching gesture. Blank background.}"
      ],
      "conteudo": "Create a wise elderly Indian sage teacher named Viśvāmitra, specialized in teaching \nchildren. He should have a gentle, humble appearance with traditional Indian spiritual \nteacher characteristics - possibly graying hair, kind eyes, wearing simple traditional \nrobes suitable for a teacher in ancient Kapilavastu. His posture should convey \nhumility and wisdom, perhaps in a teaching gesture. Blank background.}"
    }
  ]
}